<?xml version="1.0" encoding="utf-8"?>
<Directory Name="entdata">
  <File Name="1113087880.entxml" CRC32="0x72C630FF" Size="608" CompressionType="8" Encrypted="False" />
  <File Name="1188672975.entxml" CRC32="0xF076270F" Size="527" CompressionType="8" Encrypted="False" />
  <File Name="1242981249.entxml" CRC32="0x07A46C17" Size="610" CompressionType="8" Encrypted="False" />
  <File Name="1248430999.entxml" CRC32="0x64E516F2" Size="1446" CompressionType="8" Encrypted="False" />
  <File Name="1291567781.entxml" CRC32="0x6D78C7F7" Size="518" CompressionType="8" Encrypted="False" />
  <File Name="1324114427.entxml" CRC32="0xCA053D1F" Size="525" CompressionType="8" Encrypted="False" />
  <File Name="1429158610.entxml" CRC32="0xF5332247" Size="1488" CompressionType="8" Encrypted="False" />
  <File Name="1500391847.entxml" CRC32="0x28B42DFC" Size="611" CompressionType="8" Encrypted="False" />
  <File Name="1665866177.entxml" CRC32="0x7732B1F5" Size="665" CompressionType="8" Encrypted="False" />
  <File Name="17837917.entxml" CRC32="0x0A0DDF43" Size="603" CompressionType="8" Encrypted="False" />
  <File Name="1784162401.entxml" CRC32="0x385F2FBA" Size="528" CompressionType="8" Encrypted="False" />
  <File Name="1836505337.entxml" CRC32="0x23112FA4" Size="598" CompressionType="8" Encrypted="False" />
  <File Name="2027823038.entxml" CRC32="0xB3D267C4" Size="516" CompressionType="8" Encrypted="False" />
  <File Name="2034749989.entxml" CRC32="0xF0B08C29" Size="518" CompressionType="8" Encrypted="False" />
  <File Name="209406493.entxml" CRC32="0x356CD51D" Size="547" CompressionType="8" Encrypted="False" />
  <File Name="224601582.entxml" CRC32="0xB099393B" Size="610" CompressionType="8" Encrypted="False" />
  <File Name="2273622553.entxml" CRC32="0xDBBA0AB1" Size="613" CompressionType="8" Encrypted="False" />
  <File Name="2382948649.entxml" CRC32="0x5DA478B8" Size="618" CompressionType="8" Encrypted="False" />
  <File Name="25405013.entxml" CRC32="0xF0F75051" Size="605" CompressionType="8" Encrypted="False" />
  <File Name="2688720198.entxml" CRC32="0x10B29EDF" Size="663" CompressionType="8" Encrypted="False" />
  <File Name="2728743333.entxml" CRC32="0xB1A581DB" Size="519" CompressionType="8" Encrypted="False" />
  <File Name="2786621098.entxml" CRC32="0x1DE08820" Size="586" CompressionType="8" Encrypted="False" />
  <File Name="2821790400.entxml" CRC32="0x7D2BA644" Size="652" CompressionType="8" Encrypted="False" />
  <File Name="287092737.entxml" CRC32="0xB8B6C33D" Size="609" CompressionType="8" Encrypted="False" />
  <File Name="2913508753.entxml" CRC32="0xFFF04633" Size="677" CompressionType="8" Encrypted="False" />
  <File Name="2924221587.entxml" CRC32="0x22745853" Size="639" CompressionType="8" Encrypted="False" />
  <File Name="2942747397.entxml" CRC32="0x79EB4066" Size="657" CompressionType="8" Encrypted="False" />
  <File Name="303233587.entxml" CRC32="0x812AFA1F" Size="604" CompressionType="8" Encrypted="False" />
  <File Name="3079965327.entxml" CRC32="0xE17C5F95" Size="1478" CompressionType="8" Encrypted="False" />
  <File Name="3084586068.entxml" CRC32="0x42955CCA" Size="511" CompressionType="8" Encrypted="False" />
  <File Name="3094171192.entxml" CRC32="0x1D4D1704" Size="564" CompressionType="8" Encrypted="False" />
  <File Name="3238921149.entxml" CRC32="0xD2676EFF" Size="640" CompressionType="8" Encrypted="False" />
  <File Name="3411832604.entxml" CRC32="0x969C0D4E" Size="526" CompressionType="8" Encrypted="False" />
  <File Name="3470971064.entxml" CRC32="0x8192D65D" Size="629" CompressionType="8" Encrypted="False" />
  <File Name="3665579500.entxml" CRC32="0x00211D3C" Size="612" CompressionType="8" Encrypted="False" />
  <File Name="3714196999.entxml" CRC32="0x3EA9B30E" Size="1446" CompressionType="8" Encrypted="False" />
  <File Name="3802818383.entxml" CRC32="0x4EF37A94" Size="692" CompressionType="8" Encrypted="False" />
  <File Name="3811584409.entxml" CRC32="0x170820AD" Size="686" CompressionType="8" Encrypted="False" />
  <File Name="3818136471.entxml" CRC32="0x7F71B36B" Size="653" CompressionType="8" Encrypted="False" />
  <File Name="3853541131.entxml" CRC32="0xDB039A20" Size="639" CompressionType="8" Encrypted="False" />
  <File Name="3950746037.entxml" CRC32="0x0D19B9F5" Size="581" CompressionType="8" Encrypted="False" />
  <File Name="4013944431.entxml" CRC32="0xEC74C815" Size="527" CompressionType="8" Encrypted="False" />
  <File Name="4049298172.entxml" CRC32="0x477A9A9E" Size="508" CompressionType="8" Encrypted="False" />
  <File Name="4060423460.entxml" CRC32="0xD90C8BB0" Size="595" CompressionType="8" Encrypted="False" />
  <File Name="495025177.entxml" CRC32="0x95D26008" Size="654" CompressionType="8" Encrypted="False" />
  <File Name="61179837.entxml" CRC32="0x010BCF87" Size="603" CompressionType="8" Encrypted="False" />
  <File Name="672781572.entxml" CRC32="0x2FA2DC0A" Size="605" CompressionType="8" Encrypted="False" />
  <File Name="817913044.entxml" CRC32="0x20C697CD" Size="612" CompressionType="8" Encrypted="False" />
  <File Name="834687447.entxml" CRC32="0x972C11A4" Size="1488" CompressionType="8" Encrypted="False" />
  <File Name="934113612.entxml" CRC32="0x96A27D9F" Size="510" CompressionType="8" Encrypted="False" />
  <File Name="934596515.entxml" CRC32="0x8ABC00B5" Size="1468" CompressionType="8" Encrypted="False" />
  <File Name="95920695.entxml" CRC32="0x2EDA9A59" Size="666" CompressionType="8" Encrypted="False" />
</Directory>