<?xml version="1.0" encoding="utf-8"?>
<Directory Name="entdata">
  <File Name="1184820898.entxml" CRC32="0x76944D9A" Size="7523" CompressionType="8" Encrypted="False" />
  <File Name="1234262321.entxml" CRC32="0x14B3A454" Size="7644" CompressionType="8" Encrypted="False" />
  <File Name="1236733736.entxml" CRC32="0x90CECF45" Size="7583" CompressionType="8" Encrypted="False" />
  <File Name="1381278423.entxml" CRC32="0x705FD1A6" Size="937" CompressionType="8" Encrypted="False" />
  <File Name="1382981525.entxml" CRC32="0x7FD68DD2" Size="7526" CompressionType="8" Encrypted="False" />
  <File Name="1410130417.entxml" CRC32="0xF7BFB85C" Size="952" CompressionType="8" Encrypted="False" />
  <File Name="1489811936.entxml" CRC32="0x78F2EA66" Size="7599" CompressionType="8" Encrypted="False" />
  <File Name="1588130435.entxml" CRC32="0x1A534A86" Size="7590" CompressionType="8" Encrypted="False" />
  <File Name="1697372970.entxml" CRC32="0x09A2B5A8" Size="976" CompressionType="8" Encrypted="False" />
  <File Name="1716803233.entxml" CRC32="0xC50EA981" Size="7445" CompressionType="8" Encrypted="False" />
  <File Name="1724665987.entxml" CRC32="0xB851BC05" Size="7558" CompressionType="8" Encrypted="False" />
  <File Name="1786985052.entxml" CRC32="0xD014876A" Size="7503" CompressionType="8" Encrypted="False" />
  <File Name="1911017234.entxml" CRC32="0xE7A14067" Size="7628" CompressionType="8" Encrypted="False" />
  <File Name="1937253597.entxml" CRC32="0x3ED08CD2" Size="7590" CompressionType="8" Encrypted="False" />
  <File Name="2009528997.entxml" CRC32="0xC3DCF933" Size="976" CompressionType="8" Encrypted="False" />
  <File Name="2033972371.entxml" CRC32="0xD93A161F" Size="7580" CompressionType="8" Encrypted="False" />
  <File Name="2039298268.entxml" CRC32="0x58EE814B" Size="959" CompressionType="8" Encrypted="False" />
  <File Name="21001029.entxml" CRC32="0x69DAD102" Size="7609" CompressionType="8" Encrypted="False" />
  <File Name="2240744923.entxml" CRC32="0x2ED2E5A5" Size="7502" CompressionType="8" Encrypted="False" />
  <File Name="2541486395.entxml" CRC32="0x2C3AF585" Size="7584" CompressionType="8" Encrypted="False" />
  <File Name="2646575644.entxml" CRC32="0xED808C32" Size="950" CompressionType="8" Encrypted="False" />
  <File Name="2845044543.entxml" CRC32="0x722B1D12" Size="7539" CompressionType="8" Encrypted="False" />
  <File Name="322466073.entxml" CRC32="0x907F891B" Size="927" CompressionType="8" Encrypted="False" />
  <File Name="3254898522.entxml" CRC32="0x0FB44C63" Size="7558" CompressionType="8" Encrypted="False" />
  <File Name="3299394889.entxml" CRC32="0xEBE536D2" Size="7502" CompressionType="8" Encrypted="False" />
  <File Name="3349050003.entxml" CRC32="0x0304A3F1" Size="976" CompressionType="8" Encrypted="False" />
  <File Name="3360362703.entxml" CRC32="0x6A7CCACA" Size="7599" CompressionType="8" Encrypted="False" />
  <File Name="3603264245.entxml" CRC32="0x41F64BFC" Size="7604" CompressionType="8" Encrypted="False" />
  <File Name="3734514291.entxml" CRC32="0x2FB7D6B4" Size="7522" CompressionType="8" Encrypted="False" />
  <File Name="3741893593.entxml" CRC32="0x7F62584E" Size="7604" CompressionType="8" Encrypted="False" />
  <File Name="3770921332.entxml" CRC32="0x213B9FA0" Size="7584" CompressionType="8" Encrypted="False" />
  <File Name="3803628309.entxml" CRC32="0x487072D1" Size="967" CompressionType="8" Encrypted="False" />
  <File Name="3904012071.entxml" CRC32="0x4207E87B" Size="7498" CompressionType="8" Encrypted="False" />
  <File Name="3939449770.entxml" CRC32="0xF0483BBA" Size="7504" CompressionType="8" Encrypted="False" />
  <File Name="3977989229.entxml" CRC32="0xE1B8FC97" Size="927" CompressionType="8" Encrypted="False" />
  <File Name="4056835498.entxml" CRC32="0x3970FE70" Size="984" CompressionType="8" Encrypted="False" />
  <File Name="4108673470.entxml" CRC32="0x2378EC79" Size="7500" CompressionType="8" Encrypted="False" />
  <File Name="4239357048.entxml" CRC32="0x5E7E9F16" Size="7507" CompressionType="8" Encrypted="False" />
  <File Name="526903292.entxml" CRC32="0x1DF81C53" Size="7612" CompressionType="8" Encrypted="False" />
  <File Name="543201765.entxml" CRC32="0xBEC07823" Size="919" CompressionType="8" Encrypted="False" />
  <File Name="580754865.entxml" CRC32="0x1C87EA4B" Size="2122" CompressionType="8" Encrypted="False" />
  <File Name="646321175.entxml" CRC32="0xED78E2D5" Size="7600" CompressionType="8" Encrypted="False" />
  <File Name="778837084.entxml" CRC32="0x46B8154A" Size="970" CompressionType="8" Encrypted="False" />
  <File Name="852224419.entxml" CRC32="0x33B92767" Size="7595" CompressionType="8" Encrypted="False" />
  <File Name="863270217.entxml" CRC32="0xA63B8BFB" Size="7590" CompressionType="8" Encrypted="False" />
</Directory>