<?xml version="1.0" encoding="utf-8"?>
<Directory Name="entdata">
  <File Name="1126012535.entxml" CRC32="0x0CB34E87" Size="3159" CompressionType="8" Encrypted="False" />
  <File Name="1295506296.entxml" CRC32="0xD43A7A6A" Size="3150" CompressionType="8" Encrypted="False" />
  <File Name="2125086104.entxml" CRC32="0xE1C5B566" Size="3158" CompressionType="8" Encrypted="False" />
  <File Name="3229937995.entxml" CRC32="0x5DBF14AA" Size="3159" CompressionType="8" Encrypted="False" />
  <File Name="3443276888.entxml" CRC32="0x706FEBB8" Size="3159" CompressionType="8" Encrypted="False" />
  <File Name="3703373635.entxml" CRC32="0x4628FCDE" Size="3159" CompressionType="8" Encrypted="False" />
  <File Name="4074814798.entxml" CRC32="0xBFB0C3EE" Size="3160" CompressionType="8" Encrypted="False" />
  <File Name="713115333.entxml" CRC32="0xDB52F48D" Size="3158" CompressionType="8" Encrypted="False" />
</Directory>