<?xml version="1.0" encoding="utf-8"?>
<Directory Name="entdata">
  <File Name="2455649960.entxml" CRC32="0x4DA71366" Size="3112" CompressionType="8" Encrypted="False" />
  <File Name="2753265406.entxml" CRC32="0x86A46A4D" Size="3110" CompressionType="8" Encrypted="False" />
  <File Name="2763515899.entxml" CRC32="0x1B2CA316" Size="3108" CompressionType="8" Encrypted="False" />
  <File Name="3636595284.entxml" CRC32="0x8815BDD7" Size="3110" CompressionType="8" Encrypted="False" />
  <File Name="3743977799.entxml" CRC32="0x62595465" Size="3111" CompressionType="8" Encrypted="False" />
  <File Name="3956138486.entxml" CRC32="0xE0D9D5D4" Size="3110" CompressionType="8" Encrypted="False" />
  <File Name="4002686304.entxml" CRC32="0x7BEA351B" Size="3110" CompressionType="8" Encrypted="False" />
  <File Name="571004370.entxml" CRC32="0x16248BE9" Size="3111" CompressionType="8" Encrypted="False" />
</Directory>