<?xml version="1.0" encoding="utf-8"?>
<Directory Name="brush">
  <File Name="designer_192.cgf" CRC32="0x1ABEC0E3" Size="3052" CompressionType="8" Encrypted="False" />
  <File Name="designer_193.cgf" CRC32="0x1DE4C2DC" Size="3052" CompressionType="8" Encrypted="False" />
  <File Name="designer_194.cgf" CRC32="0x2D042691" Size="3052" CompressionType="8" Encrypted="False" />
  <File Name="designer_195.cgf" CRC32="0xF30B5F32" Size="3052" CompressionType="8" Encrypted="False" />
  <File Name="designer_196.cgf" CRC32="0x2D042691" Size="3052" CompressionType="8" Encrypted="False" />
  <File Name="designer_197.cgf" CRC32="0x1DE4C2DC" Size="3052" CompressionType="8" Encrypted="False" />
  <File Name="designer_198.cgf" CRC32="0x1ABEC0E3" Size="3052" CompressionType="8" Encrypted="False" />
  <File Name="designer_199.cgf" CRC32="0x1DE4C2DC" Size="3052" CompressionType="8" Encrypted="False" />
  <File Name="designer_200.cgf" CRC32="0x2D042691" Size="3052" CompressionType="8" Encrypted="False" />
  <File Name="designer_201.cgf" CRC32="0xF30B5F32" Size="3052" CompressionType="8" Encrypted="False" />
  <File Name="designer_202.cgf" CRC32="0x1DE4C2DC" Size="3052" CompressionType="8" Encrypted="False" />
  <File Name="designer_203.cgf" CRC32="0x2D042691" Size="3052" CompressionType="8" Encrypted="False" />
  <File Name="designer_204.cgf" CRC32="0x1ABEC0E3" Size="3052" CompressionType="8" Encrypted="False" />
  <File Name="designer_205.cgf" CRC32="0x1DE4C2DC" Size="3052" CompressionType="8" Encrypted="False" />
  <File Name="designer_206.cgf" CRC32="0x2D042691" Size="3052" CompressionType="8" Encrypted="False" />
  <File Name="designer_207.cgf" CRC32="0xF30B5F32" Size="3052" CompressionType="8" Encrypted="False" />
  <File Name="designer_208.cgf" CRC32="0x1DE4C2DC" Size="3052" CompressionType="8" Encrypted="False" />
  <File Name="designer_209.cgf" CRC32="0x2D042691" Size="3052" CompressionType="8" Encrypted="False" />
  <File Name="designer_210.cgf" CRC32="0x1ABEC0E3" Size="3052" CompressionType="8" Encrypted="False" />
  <File Name="designer_211.cgf" CRC32="0x1DE4C2DC" Size="3052" CompressionType="8" Encrypted="False" />
  <File Name="designer_212.cgf" CRC32="0x2D042691" Size="3052" CompressionType="8" Encrypted="False" />
  <File Name="designer_213.cgf" CRC32="0xF30B5F32" Size="3052" CompressionType="8" Encrypted="False" />
  <File Name="designer_214.cgf" CRC32="0x1DE4C2DC" Size="3052" CompressionType="8" Encrypted="False" />
  <File Name="designer_215.cgf" CRC32="0x2D042691" Size="3052" CompressionType="8" Encrypted="False" />
</Directory>