{
  "_RecordName_": "AsteroidFieldComposition.AsteroidField_AngularCellular",
  "_RecordId_": "c872daeb-f106-4995-98f7-5cb3933acbcb",
  "_RecordValue_": {
    "_Type_": "AsteroidFieldComposition",
    "fogDensity": 1,
    "fogNoiseScale": 1,
    "fogAlbedo": {
      "_Type_": "RGB",
      "r": 1,
      "g": 1,
      "b": 1
    },
    "asteroids": [
      {
        "_Type_": "AsteroidProcedural",
        "minScale": 0.8,
        "maxScale": 1.2,
        "minRotationSpeed": 0.3,
        "maxRotationSpeed": 0.6,
        "distributionA": 0.4,
        "distributionB": 1,
        "tint": {
          "_Type_": "RGB",
          "r": 1,
          "g": 1,
          "b": 1
        },
        "mesh": {
          "_Type_": "GlobalResourceCGF",
          "path": "Objects\\space\\3d\\asteroid\\angular_cellular_01\\angular_cellular_01_00200_01.cgf"
        },
        "material": {
          "_Type_": "GlobalResourceMaterial",
          "path": ""
        }
      },
      {
        "_Type_": "AsteroidProcedural",
        "minScale": 0.8,
        "maxScale": 1.2,
        "minRotationSpeed": 0.3,
        "maxRotationSpeed": 0.6,
        "distributionA": 0.1,
        "distributionB": 1,
        "tint": {
          "_Type_": "RGB",
          "r": 1,
          "g": 1,
          "b": 1
        },
        "mesh": {
          "_Type_": "GlobalResourceCGF",
          "path": "Objects\\space\\3d\\asteroid\\angular_cellular_01\\angular_cellular_01_00400_02.cgf"
        },
        "material": {
          "_Type_": "GlobalResourceMaterial",
          "path": ""
        }
      },
      {
        "_Type_": "AsteroidProcedural",
        "minScale": 0.8,
        "maxScale": 1.2,
        "minRotationSpeed": 0,
        "maxRotationSpeed": 0,
        "distributionA": 0.03,
        "distributionB": 1,
        "tint": {
          "_Type_": "RGB",
          "r": 1,
          "g": 1,
          "b": 1
        },
        "mesh": {
          "_Type_": "GlobalResourceCGF",
          "path": "Objects\\space\\3d\\asteroid\\angular_cellular_01\\angular_cellular_01_00800_cluster_01.cgf"
        },
        "material": {
          "_Type_": "GlobalResourceMaterial",
          "path": ""
        }
      },
      {
        "_Type_": "AsteroidProcedural",
        "minScale": 0.8,
        "maxScale": 1.2,
        "minRotationSpeed": 0.3,
        "maxRotationSpeed": 0.6,
        "distributionA": 0.04,
        "distributionB": 1,
        "tint": {
          "_Type_": "RGB",
          "r": 1,
          "g": 1,
          "b": 1
        },
        "mesh": {
          "_Type_": "GlobalResourceCGF",
          "path": "Objects\\space\\3d\\asteroid\\angular_cellular_01\\angular_cellular_01_00900_02.cgf"
        },
        "material": {
          "_Type_": "GlobalResourceMaterial",
          "path": ""
        }
      },
      {
        "_Type_": "AsteroidProcedural",
        "minScale": 0.8,
        "maxScale": 1.2,
        "minRotationSpeed": 0,
        "maxRotationSpeed": 0,
        "distributionA": 0.1,
        "distributionB": 1,
        "tint": {
          "_Type_": "RGB",
          "r": 1,
          "g": 1,
          "b": 1
        },
        "mesh": {
          "_Type_": "GlobalResourceCGF",
          "path": "Objects\\space\\3d\\asteroid\\angular_cellular_01\\angular_cellular_01_01000_cluster_01.cgf"
        },
        "material": {
          "_Type_": "GlobalResourceMaterial",
          "path": ""
        }
      },
      {
        "_Type_": "AsteroidProcedural",
        "minScale": 0.8,
        "maxScale": 1.2,
        "minRotationSpeed": 0,
        "maxRotationSpeed": 0,
        "distributionA": 0.15,
        "distributionB": 1,
        "tint": {
          "_Type_": "RGB",
          "r": 1,
          "g": 1,
          "b": 1
        },
        "mesh": {
          "_Type_": "GlobalResourceCGF",
          "path": "Objects\\space\\3d\\asteroid\\angular_cellular_01\\angular_cellular_01_01300_cluster_01.cgf"
        },
        "material": {
          "_Type_": "GlobalResourceMaterial",
          "path": ""
        }
      },
      {
        "_Type_": "AsteroidProcedural",
        "minScale": 0.8,
        "maxScale": 1.2,
        "minRotationSpeed": 0,
        "maxRotationSpeed": 0,
        "distributionA": 0.1,
        "distributionB": 1,
        "tint": {
          "_Type_": "RGB",
          "r": 1,
          "g": 1,
          "b": 1
        },
        "mesh": {
          "_Type_": "GlobalResourceCGF",
          "path": "Objects\\space\\3d\\asteroid\\angular_cellular_01\\angular_cellular_01_02800_cluster_01.cgf"
        },
        "material": {
          "_Type_": "GlobalResourceMaterial",
          "path": ""
        }
      },
      {
        "_Type_": "AsteroidProcedural",
        "minScale": 0.8,
        "maxScale": 1.2,
        "minRotationSpeed": 0,
        "maxRotationSpeed": 0,
        "distributionA": 0.1,
        "distributionB": 1,
        "tint": {
          "_Type_": "RGB",
          "r": 1,
          "g": 1,
          "b": 1
        },
        "mesh": {
          "_Type_": "GlobalResourceCGF",
          "path": "Objects\\space\\3d\\asteroid\\angular_cellular_01\\angular_cellular_01_03100_cluster_01.cgf"
        },
        "material": {
          "_Type_": "GlobalResourceMaterial",
          "path": ""
        }
      }
    ]
  }
}