<?xml version="1.0" encoding="utf-8"?>
<Directory Name="entdata">
  <File Name="1012460085.entxml" CRC32="0x9EDA8A48" Size="3825" CompressionType="8" Encrypted="False" />
  <File Name="1022999305.entxml" CRC32="0xF921A02C" Size="3890" CompressionType="8" Encrypted="False" />
  <File Name="1024472167.entxml" CRC32="0x31043279" Size="3822" CompressionType="8" Encrypted="False" />
  <File Name="1035275823.entxml" CRC32="0x8EDCAA94" Size="3824" CompressionType="8" Encrypted="False" />
  <File Name="1085072461.entxml" CRC32="0xAA9F6BD0" Size="3806" CompressionType="8" Encrypted="False" />
  <File Name="1087889790.entxml" CRC32="0x418EDC27" Size="3821" CompressionType="8" Encrypted="False" />
  <File Name="1095818406.entxml" CRC32="0x384B15B1" Size="3820" CompressionType="8" Encrypted="False" />
  <File Name="1101675905.entxml" CRC32="0x0D92674E" Size="3809" CompressionType="8" Encrypted="False" />
  <File Name="110766762.entxml" CRC32="0x403878F6" Size="3822" CompressionType="8" Encrypted="False" />
  <File Name="1117134694.entxml" CRC32="0xD8190F70" Size="3827" CompressionType="8" Encrypted="False" />
  <File Name="1149338695.entxml" CRC32="0x3BBD0998" Size="3820" CompressionType="8" Encrypted="False" />
  <File Name="1154654296.entxml" CRC32="0x112D98E2" Size="3813" CompressionType="8" Encrypted="False" />
  <File Name="1161173596.entxml" CRC32="0x80051FEC" Size="3823" CompressionType="8" Encrypted="False" />
  <File Name="1173928406.entxml" CRC32="0xFFE43206" Size="3826" CompressionType="8" Encrypted="False" />
  <File Name="1181752558.entxml" CRC32="0x54CF90A0" Size="3821" CompressionType="8" Encrypted="False" />
  <File Name="1192023020.entxml" CRC32="0xB8A32E41" Size="3824" CompressionType="8" Encrypted="False" />
  <File Name="119235552.entxml" CRC32="0x5682D3C0" Size="3818" CompressionType="8" Encrypted="False" />
  <File Name="1195034980.entxml" CRC32="0xAE7369DA" Size="3823" CompressionType="8" Encrypted="False" />
  <File Name="120083245.entxml" CRC32="0x722F46FA" Size="3825" CompressionType="8" Encrypted="False" />
  <File Name="1203485360.entxml" CRC32="0x0F71614C" Size="3817" CompressionType="8" Encrypted="False" />
  <File Name="1213940983.entxml" CRC32="0x908E8ED9" Size="3825" CompressionType="8" Encrypted="False" />
  <File Name="1221698771.entxml" CRC32="0x05924CBF" Size="3811" CompressionType="8" Encrypted="False" />
  <File Name="1234748488.entxml" CRC32="0x3F4DF8D1" Size="3823" CompressionType="8" Encrypted="False" />
  <File Name="1235307051.entxml" CRC32="0xF503CB8C" Size="3823" CompressionType="8" Encrypted="False" />
  <File Name="1239476495.entxml" CRC32="0x451F75B5" Size="3827" CompressionType="8" Encrypted="False" />
  <File Name="1241429800.entxml" CRC32="0xE8E306C5" Size="3821" CompressionType="8" Encrypted="False" />
  <File Name="1248710991.entxml" CRC32="0xA196A553" Size="3821" CompressionType="8" Encrypted="False" />
  <File Name="1256659862.entxml" CRC32="0xAA6786BD" Size="3823" CompressionType="8" Encrypted="False" />
  <File Name="1262302457.entxml" CRC32="0x0D33691F" Size="3822" CompressionType="8" Encrypted="False" />
  <File Name="1276726446.entxml" CRC32="0x26DBED98" Size="3892" CompressionType="8" Encrypted="False" />
  <File Name="129099924.entxml" CRC32="0x62D7F08D" Size="3801" CompressionType="8" Encrypted="False" />
  <File Name="1314979628.entxml" CRC32="0x7BBD249F" Size="3820" CompressionType="8" Encrypted="False" />
  <File Name="1316889894.entxml" CRC32="0xFA111F93" Size="3823" CompressionType="8" Encrypted="False" />
  <File Name="1345395423.entxml" CRC32="0x8E617B98" Size="3810" CompressionType="8" Encrypted="False" />
  <File Name="1406998956.entxml" CRC32="0x5F78A67F" Size="1021" CompressionType="8" Encrypted="False" />
  <File Name="1409625367.entxml" CRC32="0x90A1CC56" Size="3820" CompressionType="8" Encrypted="False" />
  <File Name="1411387440.entxml" CRC32="0xE4BEE0E2" Size="3817" CompressionType="8" Encrypted="False" />
  <File Name="1424290552.entxml" CRC32="0xD57F940E" Size="3811" CompressionType="8" Encrypted="False" />
  <File Name="1437395904.entxml" CRC32="0xC0C74EE7" Size="3820" CompressionType="8" Encrypted="False" />
  <File Name="1514501991.entxml" CRC32="0x03D49931" Size="3810" CompressionType="8" Encrypted="False" />
  <File Name="154941511.entxml" CRC32="0xD18B81B3" Size="3822" CompressionType="8" Encrypted="False" />
  <File Name="1568252181.entxml" CRC32="0xDB35B266" Size="3821" CompressionType="8" Encrypted="False" />
  <File Name="1570709085.entxml" CRC32="0xFD8EEF93" Size="3820" CompressionType="8" Encrypted="False" />
  <File Name="1571886805.entxml" CRC32="0xFC464119" Size="3824" CompressionType="8" Encrypted="False" />
  <File Name="1591621906.entxml" CRC32="0xBDEDA4A6" Size="3818" CompressionType="8" Encrypted="False" />
  <File Name="1607876673.entxml" CRC32="0x94F81DE0" Size="3826" CompressionType="8" Encrypted="False" />
  <File Name="1616155083.entxml" CRC32="0x3F49B9AC" Size="3818" CompressionType="8" Encrypted="False" />
  <File Name="1619523368.entxml" CRC32="0xD33E2771" Size="3824" CompressionType="8" Encrypted="False" />
  <File Name="1625236199.entxml" CRC32="0xC3157D21" Size="3882" CompressionType="8" Encrypted="False" />
  <File Name="1635709354.entxml" CRC32="0x24F5A960" Size="3824" CompressionType="8" Encrypted="False" />
  <File Name="1643625835.entxml" CRC32="0x58FAF4C5" Size="3823" CompressionType="8" Encrypted="False" />
  <File Name="165620909.entxml" CRC32="0xA726DBEF" Size="3820" CompressionType="8" Encrypted="False" />
  <File Name="1665501889.entxml" CRC32="0x26DD6A21" Size="3823" CompressionType="8" Encrypted="False" />
  <File Name="1668055428.entxml" CRC32="0x51167159" Size="3813" CompressionType="8" Encrypted="False" />
  <File Name="1672512228.entxml" CRC32="0x318FECEE" Size="3810" CompressionType="8" Encrypted="False" />
  <File Name="1679513228.entxml" CRC32="0x67302EBC" Size="3822" CompressionType="8" Encrypted="False" />
  <File Name="1688125093.entxml" CRC32="0x660828AD" Size="3819" CompressionType="8" Encrypted="False" />
  <File Name="1709313559.entxml" CRC32="0xAC05DCA4" Size="3812" CompressionType="8" Encrypted="False" />
  <File Name="1713060868.entxml" CRC32="0x38429739" Size="3822" CompressionType="8" Encrypted="False" />
  <File Name="1719701079.entxml" CRC32="0x592AB72A" Size="3825" CompressionType="8" Encrypted="False" />
  <File Name="1721592110.entxml" CRC32="0x22E461B5" Size="3814" CompressionType="8" Encrypted="False" />
  <File Name="1725107871.entxml" CRC32="0x52E8A379" Size="3821" CompressionType="8" Encrypted="False" />
  <File Name="1725397913.entxml" CRC32="0x3227825A" Size="3810" CompressionType="8" Encrypted="False" />
  <File Name="1726152553.entxml" CRC32="0x98D6BD92" Size="3824" CompressionType="8" Encrypted="False" />
  <File Name="1726932179.entxml" CRC32="0x450EB65D" Size="3824" CompressionType="8" Encrypted="False" />
  <File Name="1759895233.entxml" CRC32="0x8D7E2BEA" Size="3821" CompressionType="8" Encrypted="False" />
  <File Name="1760027701.entxml" CRC32="0x408E8084" Size="3817" CompressionType="8" Encrypted="False" />
  <File Name="1779503524.entxml" CRC32="0xC8AFCB37" Size="3824" CompressionType="8" Encrypted="False" />
  <File Name="1784186297.entxml" CRC32="0x6887FF0D" Size="3808" CompressionType="8" Encrypted="False" />
  <File Name="1808389065.entxml" CRC32="0xE3B7C637" Size="3813" CompressionType="8" Encrypted="False" />
  <File Name="1824475829.entxml" CRC32="0x3755043B" Size="3815" CompressionType="8" Encrypted="False" />
  <File Name="1846243361.entxml" CRC32="0xD90E9715" Size="3823" CompressionType="8" Encrypted="False" />
  <File Name="184837314.entxml" CRC32="0x1BE575CA" Size="3809" CompressionType="8" Encrypted="False" />
  <File Name="1895347065.entxml" CRC32="0x3FD841AE" Size="3824" CompressionType="8" Encrypted="False" />
  <File Name="190087603.entxml" CRC32="0xD8F1B991" Size="3818" CompressionType="8" Encrypted="False" />
  <File Name="1916037894.entxml" CRC32="0x0497849B" Size="3890" CompressionType="8" Encrypted="False" />
  <File Name="1938860837.entxml" CRC32="0x28E0A51E" Size="3811" CompressionType="8" Encrypted="False" />
  <File Name="1942785435.entxml" CRC32="0x77E97516" Size="3820" CompressionType="8" Encrypted="False" />
  <File Name="1942887562.entxml" CRC32="0x900C9B99" Size="3824" CompressionType="8" Encrypted="False" />
  <File Name="1955616335.entxml" CRC32="0xFDA8DBE5" Size="3825" CompressionType="8" Encrypted="False" />
  <File Name="1985008959.entxml" CRC32="0x198C53B3" Size="3812" CompressionType="8" Encrypted="False" />
  <File Name="1993141873.entxml" CRC32="0xAA0F61CB" Size="3821" CompressionType="8" Encrypted="False" />
  <File Name="2009619717.entxml" CRC32="0x34A784F7" Size="3889" CompressionType="8" Encrypted="False" />
  <File Name="200964368.entxml" CRC32="0xD5EB5885" Size="3813" CompressionType="8" Encrypted="False" />
  <File Name="2016832909.entxml" CRC32="0x1EA82319" Size="3826" CompressionType="8" Encrypted="False" />
  <File Name="203746750.entxml" CRC32="0x8129C071" Size="3825" CompressionType="8" Encrypted="False" />
  <File Name="2043981535.entxml" CRC32="0x272FB702" Size="3810" CompressionType="8" Encrypted="False" />
  <File Name="2053769223.entxml" CRC32="0x64C8E124" Size="3822" CompressionType="8" Encrypted="False" />
  <File Name="2057191973.entxml" CRC32="0x0C078030" Size="3823" CompressionType="8" Encrypted="False" />
  <File Name="206824547.entxml" CRC32="0x890829AA" Size="3822" CompressionType="8" Encrypted="False" />
  <File Name="2072958103.entxml" CRC32="0x7BA76F54" Size="3827" CompressionType="8" Encrypted="False" />
  <File Name="2103369260.entxml" CRC32="0xEC76A874" Size="3824" CompressionType="8" Encrypted="False" />
  <File Name="2111358950.entxml" CRC32="0xDFB0DE3B" Size="3822" CompressionType="8" Encrypted="False" />
  <File Name="2122729238.entxml" CRC32="0x0BE9A059" Size="3811" CompressionType="8" Encrypted="False" />
  <File Name="2124044559.entxml" CRC32="0x7EBC2E65" Size="3830" CompressionType="8" Encrypted="False" />
  <File Name="2126320249.entxml" CRC32="0x4852971C" Size="3828" CompressionType="8" Encrypted="False" />
  <File Name="2134858215.entxml" CRC32="0xD42745C5" Size="3818" CompressionType="8" Encrypted="False" />
  <File Name="2136944310.entxml" CRC32="0xDE970757" Size="3824" CompressionType="8" Encrypted="False" />
  <File Name="2138380246.entxml" CRC32="0x22EC523E" Size="3821" CompressionType="8" Encrypted="False" />
  <File Name="2145919834.entxml" CRC32="0x5FC15A99" Size="3820" CompressionType="8" Encrypted="False" />
  <File Name="2150338977.entxml" CRC32="0x81416803" Size="3811" CompressionType="8" Encrypted="False" />
  <File Name="2165816722.entxml" CRC32="0x56A864A5" Size="3819" CompressionType="8" Encrypted="False" />
  <File Name="2173267392.entxml" CRC32="0x7BE4FD51" Size="3822" CompressionType="8" Encrypted="False" />
  <File Name="2179475568.entxml" CRC32="0x2B9785BF" Size="3811" CompressionType="8" Encrypted="False" />
  <File Name="2196254286.entxml" CRC32="0xDC657DDE" Size="3823" CompressionType="8" Encrypted="False" />
  <File Name="2203840985.entxml" CRC32="0x2DA2E716" Size="3821" CompressionType="8" Encrypted="False" />
  <File Name="2247596097.entxml" CRC32="0x94A71B7D" Size="3816" CompressionType="8" Encrypted="False" />
  <File Name="2247861915.entxml" CRC32="0x740013B9" Size="3826" CompressionType="8" Encrypted="False" />
  <File Name="2256031000.entxml" CRC32="0x66F42972" Size="3826" CompressionType="8" Encrypted="False" />
  <File Name="2257025852.entxml" CRC32="0xA99F6E3C" Size="3812" CompressionType="8" Encrypted="False" />
  <File Name="226453212.entxml" CRC32="0xC3C547A8" Size="3822" CompressionType="8" Encrypted="False" />
  <File Name="2266821275.entxml" CRC32="0x4F65B683" Size="3820" CompressionType="8" Encrypted="False" />
  <File Name="2274501626.entxml" CRC32="0x6639D2E0" Size="3822" CompressionType="8" Encrypted="False" />
  <File Name="2303271099.entxml" CRC32="0x8B09656E" Size="3813" CompressionType="8" Encrypted="False" />
  <File Name="2304643241.entxml" CRC32="0x1D0B5BA5" Size="3822" CompressionType="8" Encrypted="False" />
  <File Name="2314338311.entxml" CRC32="0x35514A0E" Size="3808" CompressionType="8" Encrypted="False" />
  <File Name="2392299983.entxml" CRC32="0x44842937" Size="3824" CompressionType="8" Encrypted="False" />
  <File Name="2424302904.entxml" CRC32="0xB426485C" Size="3820" CompressionType="8" Encrypted="False" />
  <File Name="2431969633.entxml" CRC32="0x0EEDDFB4" Size="3824" CompressionType="8" Encrypted="False" />
  <File Name="2440731246.entxml" CRC32="0x075C86EC" Size="3819" CompressionType="8" Encrypted="False" />
  <File Name="2448805042.entxml" CRC32="0xB4508228" Size="3827" CompressionType="8" Encrypted="False" />
  <File Name="246340590.entxml" CRC32="0x7DAA8122" Size="3820" CompressionType="8" Encrypted="False" />
  <File Name="2477321617.entxml" CRC32="0xF2812B17" Size="3822" CompressionType="8" Encrypted="False" />
  <File Name="250333675.entxml" CRC32="0x3DBA9144" Size="3817" CompressionType="8" Encrypted="False" />
  <File Name="2504844059.entxml" CRC32="0x91D0BDC6" Size="3824" CompressionType="8" Encrypted="False" />
  <File Name="250568917.entxml" CRC32="0x8E65D3AF" Size="3821" CompressionType="8" Encrypted="False" />
  <File Name="2517264428.entxml" CRC32="0x0F1DF9F3" Size="3824" CompressionType="8" Encrypted="False" />
  <File Name="2524679845.entxml" CRC32="0xDEA6016E" Size="3822" CompressionType="8" Encrypted="False" />
  <File Name="2544311317.entxml" CRC32="0x92437B90" Size="3822" CompressionType="8" Encrypted="False" />
  <File Name="2575188965.entxml" CRC32="0xF0B23779" Size="3822" CompressionType="8" Encrypted="False" />
  <File Name="2577090097.entxml" CRC32="0xB8ACB341" Size="3824" CompressionType="8" Encrypted="False" />
  <File Name="2590340270.entxml" CRC32="0xDBEA42E3" Size="3823" CompressionType="8" Encrypted="False" />
  <File Name="2610684795.entxml" CRC32="0x69B918BC" Size="3819" CompressionType="8" Encrypted="False" />
  <File Name="2615998515.entxml" CRC32="0x11D2CE17" Size="3826" CompressionType="8" Encrypted="False" />
  <File Name="2632306588.entxml" CRC32="0xECBFCDB4" Size="3824" CompressionType="8" Encrypted="False" />
  <File Name="2640008150.entxml" CRC32="0xCB641D6E" Size="3818" CompressionType="8" Encrypted="False" />
  <File Name="2668268597.entxml" CRC32="0x0CCBC1E1" Size="3827" CompressionType="8" Encrypted="False" />
  <File Name="2669268785.entxml" CRC32="0x5678568A" Size="3827" CompressionType="8" Encrypted="False" />
  <File Name="2706255730.entxml" CRC32="0x11C916A6" Size="3821" CompressionType="8" Encrypted="False" />
  <File Name="270904210.entxml" CRC32="0x6EF72060" Size="3891" CompressionType="8" Encrypted="False" />
  <File Name="2714262358.entxml" CRC32="0x7A841CEE" Size="3822" CompressionType="8" Encrypted="False" />
  <File Name="2732720823.entxml" CRC32="0x2AE06BE9" Size="3821" CompressionType="8" Encrypted="False" />
  <File Name="2746084074.entxml" CRC32="0xE61EF635" Size="3823" CompressionType="8" Encrypted="False" />
  <File Name="2757635082.entxml" CRC32="0x665E3910" Size="3819" CompressionType="8" Encrypted="False" />
  <File Name="2759026202.entxml" CRC32="0x3D9E96E3" Size="3820" CompressionType="8" Encrypted="False" />
  <File Name="2772906530.entxml" CRC32="0x7594E4E5" Size="3819" CompressionType="8" Encrypted="False" />
  <File Name="2774701052.entxml" CRC32="0xC151B5AA" Size="3819" CompressionType="8" Encrypted="False" />
  <File Name="2779139271.entxml" CRC32="0xBE51D249" Size="3821" CompressionType="8" Encrypted="False" />
  <File Name="2808479584.entxml" CRC32="0xB9C98AC4" Size="3814" CompressionType="8" Encrypted="False" />
  <File Name="2820062665.entxml" CRC32="0x010A10D5" Size="3818" CompressionType="8" Encrypted="False" />
  <File Name="2836643172.entxml" CRC32="0xBF32E169" Size="3822" CompressionType="8" Encrypted="False" />
  <File Name="2897263214.entxml" CRC32="0x446619B0" Size="3825" CompressionType="8" Encrypted="False" />
  <File Name="2905581019.entxml" CRC32="0x8389ABEC" Size="3812" CompressionType="8" Encrypted="False" />
  <File Name="2907559065.entxml" CRC32="0x435491D4" Size="3818" CompressionType="8" Encrypted="False" />
  <File Name="2927847386.entxml" CRC32="0xB08A2B62" Size="3821" CompressionType="8" Encrypted="False" />
  <File Name="2928973055.entxml" CRC32="0x4E940860" Size="3822" CompressionType="8" Encrypted="False" />
  <File Name="2965469856.entxml" CRC32="0xA66F1F00" Size="3822" CompressionType="8" Encrypted="False" />
  <File Name="2993955782.entxml" CRC32="0x3AF17AC7" Size="3893" CompressionType="8" Encrypted="False" />
  <File Name="2995895159.entxml" CRC32="0x0056CEA6" Size="3819" CompressionType="8" Encrypted="False" />
  <File Name="3009538676.entxml" CRC32="0x2CD67D1C" Size="3825" CompressionType="8" Encrypted="False" />
  <File Name="3017405074.entxml" CRC32="0xB342560F" Size="3819" CompressionType="8" Encrypted="False" />
  <File Name="3048093705.entxml" CRC32="0x4F24BD3E" Size="3808" CompressionType="8" Encrypted="False" />
  <File Name="3049784568.entxml" CRC32="0x8B729732" Size="3819" CompressionType="8" Encrypted="False" />
  <File Name="3049801257.entxml" CRC32="0x18D6C117" Size="3820" CompressionType="8" Encrypted="False" />
  <File Name="3052479244.entxml" CRC32="0x9D80F215" Size="3817" CompressionType="8" Encrypted="False" />
  <File Name="3065077419.entxml" CRC32="0x647F671C" Size="3824" CompressionType="8" Encrypted="False" />
  <File Name="307967244.entxml" CRC32="0x6890306D" Size="3892" CompressionType="8" Encrypted="False" />
  <File Name="3093905179.entxml" CRC32="0x91FC3ED1" Size="3869" CompressionType="8" Encrypted="False" />
  <File Name="3096719840.entxml" CRC32="0x4F8BDD58" Size="3822" CompressionType="8" Encrypted="False" />
  <File Name="3107530961.entxml" CRC32="0x4E1ABE0F" Size="3827" CompressionType="8" Encrypted="False" />
  <File Name="3115603604.entxml" CRC32="0xA9D7034D" Size="3821" CompressionType="8" Encrypted="False" />
  <File Name="3178885480.entxml" CRC32="0xAF12BA08" Size="3820" CompressionType="8" Encrypted="False" />
  <File Name="3193029056.entxml" CRC32="0x4060E123" Size="3822" CompressionType="8" Encrypted="False" />
  <File Name="3217497602.entxml" CRC32="0x4DE16390" Size="3824" CompressionType="8" Encrypted="False" />
  <File Name="3236258349.entxml" CRC32="0x8D6A4329" Size="3821" CompressionType="8" Encrypted="False" />
  <File Name="3242986927.entxml" CRC32="0x49BFD5B1" Size="3822" CompressionType="8" Encrypted="False" />
  <File Name="3254264309.entxml" CRC32="0x7E429002" Size="3819" CompressionType="8" Encrypted="False" />
  <File Name="3254567622.entxml" CRC32="0xA69404C0" Size="3822" CompressionType="8" Encrypted="False" />
  <File Name="3265269830.entxml" CRC32="0x617C8A33" Size="3820" CompressionType="8" Encrypted="False" />
  <File Name="3270103982.entxml" CRC32="0xCAD661D2" Size="3827" CompressionType="8" Encrypted="False" />
  <File Name="3276414593.entxml" CRC32="0xD5FAC6C2" Size="959" CompressionType="8" Encrypted="False" />
  <File Name="3296393192.entxml" CRC32="0x14E7AE68" Size="3819" CompressionType="8" Encrypted="False" />
  <File Name="3320215776.entxml" CRC32="0x126A895F" Size="3820" CompressionType="8" Encrypted="False" />
  <File Name="3327996786.entxml" CRC32="0x817B0005" Size="3828" CompressionType="8" Encrypted="False" />
  <File Name="3345776175.entxml" CRC32="0xFE8BA6DE" Size="3818" CompressionType="8" Encrypted="False" />
  <File Name="3346482556.entxml" CRC32="0xEA60A941" Size="3822" CompressionType="8" Encrypted="False" />
  <File Name="3352724710.entxml" CRC32="0x8FA4B247" Size="3818" CompressionType="8" Encrypted="False" />
  <File Name="3364100010.entxml" CRC32="0xA7836819" Size="3810" CompressionType="8" Encrypted="False" />
  <File Name="3372259595.entxml" CRC32="0x381CDF27" Size="3824" CompressionType="8" Encrypted="False" />
  <File Name="3376112147.entxml" CRC32="0x8B142A9E" Size="3827" CompressionType="8" Encrypted="False" />
  <File Name="3382200215.entxml" CRC32="0xC9143BAC" Size="3819" CompressionType="8" Encrypted="False" />
  <File Name="3414625201.entxml" CRC32="0xD7F5599C" Size="3830" CompressionType="8" Encrypted="False" />
  <File Name="3439153644.entxml" CRC32="0x2C542E8D" Size="3818" CompressionType="8" Encrypted="False" />
  <File Name="3439813184.entxml" CRC32="0x8501E075" Size="3889" CompressionType="8" Encrypted="False" />
  <File Name="3451257748.entxml" CRC32="0x2957EDCC" Size="3823" CompressionType="8" Encrypted="False" />
  <File Name="3454338187.entxml" CRC32="0x0C2B6A3B" Size="3813" CompressionType="8" Encrypted="False" />
  <File Name="3490598679.entxml" CRC32="0xF7152C41" Size="3818" CompressionType="8" Encrypted="False" />
  <File Name="3493053812.entxml" CRC32="0xEA81CFA7" Size="3821" CompressionType="8" Encrypted="False" />
  <File Name="3506474248.entxml" CRC32="0x29AA7FAA" Size="3822" CompressionType="8" Encrypted="False" />
  <File Name="3523881113.entxml" CRC32="0xF8F1BB73" Size="3819" CompressionType="8" Encrypted="False" />
  <File Name="3525850328.entxml" CRC32="0x0582FFC7" Size="3828" CompressionType="8" Encrypted="False" />
  <File Name="3526283123.entxml" CRC32="0x90831210" Size="3816" CompressionType="8" Encrypted="False" />
  <File Name="3529664990.entxml" CRC32="0xE2036603" Size="1018" CompressionType="8" Encrypted="False" />
  <File Name="355405739.entxml" CRC32="0xF23EAC11" Size="3827" CompressionType="8" Encrypted="False" />
  <File Name="3563643418.entxml" CRC32="0x72B88849" Size="3814" CompressionType="8" Encrypted="False" />
  <File Name="3565276338.entxml" CRC32="0x8834EE5E" Size="3820" CompressionType="8" Encrypted="False" />
  <File Name="3574028558.entxml" CRC32="0x60B341D9" Size="3825" CompressionType="8" Encrypted="False" />
  <File Name="3592557059.entxml" CRC32="0x1F10B69C" Size="3822" CompressionType="8" Encrypted="False" />
  <File Name="359638451.entxml" CRC32="0x12FD4F6D" Size="3807" CompressionType="8" Encrypted="False" />
  <File Name="3602865445.entxml" CRC32="0x1CAA4C63" Size="3819" CompressionType="8" Encrypted="False" />
  <File Name="3621697906.entxml" CRC32="0x242D9279" Size="3809" CompressionType="8" Encrypted="False" />
  <File Name="3659758133.entxml" CRC32="0x63F80ED7" Size="3811" CompressionType="8" Encrypted="False" />
  <File Name="3662290200.entxml" CRC32="0x34DF3A03" Size="3818" CompressionType="8" Encrypted="False" />
  <File Name="3685860020.entxml" CRC32="0x45D1A156" Size="3814" CompressionType="8" Encrypted="False" />
  <File Name="3707179394.entxml" CRC32="0xAB965891" Size="3824" CompressionType="8" Encrypted="False" />
  <File Name="3710595499.entxml" CRC32="0xD2014329" Size="3811" CompressionType="8" Encrypted="False" />
  <File Name="3713708710.entxml" CRC32="0xD00F8800" Size="3824" CompressionType="8" Encrypted="False" />
  <File Name="3720348527.entxml" CRC32="0x96A838D9" Size="3820" CompressionType="8" Encrypted="False" />
  <File Name="3732448876.entxml" CRC32="0x6293DFAF" Size="3820" CompressionType="8" Encrypted="False" />
  <File Name="373316389.entxml" CRC32="0x927AE63C" Size="3821" CompressionType="8" Encrypted="False" />
  <File Name="37521698.entxml" CRC32="0xC6E664C7" Size="3823" CompressionType="8" Encrypted="False" />
  <File Name="3752793553.entxml" CRC32="0x46DF664D" Size="3819" CompressionType="8" Encrypted="False" />
  <File Name="3781377021.entxml" CRC32="0x45DCA634" Size="3886" CompressionType="8" Encrypted="False" />
  <File Name="3795100433.entxml" CRC32="0xF70708D1" Size="3825" CompressionType="8" Encrypted="False" />
  <File Name="3797079044.entxml" CRC32="0x93F99CB3" Size="3819" CompressionType="8" Encrypted="False" />
  <File Name="382667222.entxml" CRC32="0xE66AD6D3" Size="3825" CompressionType="8" Encrypted="False" />
  <File Name="3829747465.entxml" CRC32="0x87BDE274" Size="3891" CompressionType="8" Encrypted="False" />
  <File Name="3845093831.entxml" CRC32="0x47B436E6" Size="3810" CompressionType="8" Encrypted="False" />
  <File Name="3860033316.entxml" CRC32="0x516CDB7E" Size="3815" CompressionType="8" Encrypted="False" />
  <File Name="3868757422.entxml" CRC32="0x80B63929" Size="3820" CompressionType="8" Encrypted="False" />
  <File Name="3871293153.entxml" CRC32="0x1FE1D0B0" Size="3819" CompressionType="8" Encrypted="False" />
  <File Name="3889471160.entxml" CRC32="0xF1E20ED8" Size="3891" CompressionType="8" Encrypted="False" />
  <File Name="3896684260.entxml" CRC32="0x6D8FA8FD" Size="3821" CompressionType="8" Encrypted="False" />
  <File Name="3900252604.entxml" CRC32="0xC0C00C3C" Size="3822" CompressionType="8" Encrypted="False" />
  <File Name="3930338154.entxml" CRC32="0x82DFE3A2" Size="3811" CompressionType="8" Encrypted="False" />
  <File Name="3941384468.entxml" CRC32="0x0CF41203" Size="3818" CompressionType="8" Encrypted="False" />
  <File Name="3950943892.entxml" CRC32="0xDC672384" Size="3823" CompressionType="8" Encrypted="False" />
  <File Name="3980558389.entxml" CRC32="0x6819AD18" Size="3821" CompressionType="8" Encrypted="False" />
  <File Name="3980973750.entxml" CRC32="0x05DBC697" Size="3824" CompressionType="8" Encrypted="False" />
  <File Name="3985690134.entxml" CRC32="0x7CB0A5A8" Size="3893" CompressionType="8" Encrypted="False" />
  <File Name="3996182771.entxml" CRC32="0xF8E1D8A3" Size="3820" CompressionType="8" Encrypted="False" />
  <File Name="3996372404.entxml" CRC32="0x729A63A4" Size="3823" CompressionType="8" Encrypted="False" />
  <File Name="401854158.entxml" CRC32="0x40CEEBF4" Size="3819" CompressionType="8" Encrypted="False" />
  <File Name="4025223625.entxml" CRC32="0x65EB31FC" Size="3821" CompressionType="8" Encrypted="False" />
  <File Name="4031494603.entxml" CRC32="0x73B3F72D" Size="3811" CompressionType="8" Encrypted="False" />
  <File Name="4040254247.entxml" CRC32="0xD44F7F6D" Size="3822" CompressionType="8" Encrypted="False" />
  <File Name="4063588349.entxml" CRC32="0xAC94BDCA" Size="3825" CompressionType="8" Encrypted="False" />
  <File Name="4066997329.entxml" CRC32="0x47B1D116" Size="3811" CompressionType="8" Encrypted="False" />
  <File Name="4068000880.entxml" CRC32="0x0D61BA76" Size="3821" CompressionType="8" Encrypted="False" />
  <File Name="4071326062.entxml" CRC32="0x6CA01081" Size="3825" CompressionType="8" Encrypted="False" />
  <File Name="4085214151.entxml" CRC32="0x2E2ECF16" Size="3821" CompressionType="8" Encrypted="False" />
  <File Name="4093582790.entxml" CRC32="0x1D07F752" Size="3818" CompressionType="8" Encrypted="False" />
  <File Name="4105358065.entxml" CRC32="0xDFA55168" Size="3827" CompressionType="8" Encrypted="False" />
  <File Name="4115064867.entxml" CRC32="0x705DF054" Size="3820" CompressionType="8" Encrypted="False" />
  <File Name="4116367605.entxml" CRC32="0x89D8DD74" Size="3822" CompressionType="8" Encrypted="False" />
  <File Name="4118954021.entxml" CRC32="0xE1161805" Size="3827" CompressionType="8" Encrypted="False" />
  <File Name="4124429392.entxml" CRC32="0xCD92A097" Size="3821" CompressionType="8" Encrypted="False" />
  <File Name="4126345008.entxml" CRC32="0x9E12B703" Size="3891" CompressionType="8" Encrypted="False" />
  <File Name="4146669515.entxml" CRC32="0x0A0BA219" Size="3824" CompressionType="8" Encrypted="False" />
  <File Name="4175098172.entxml" CRC32="0xFD3FD897" Size="3817" CompressionType="8" Encrypted="False" />
  <File Name="4176607985.entxml" CRC32="0xC92C5095" Size="3819" CompressionType="8" Encrypted="False" />
  <File Name="4196688731.entxml" CRC32="0x97D75451" Size="3804" CompressionType="8" Encrypted="False" />
  <File Name="4213989948.entxml" CRC32="0x9ED93975" Size="3823" CompressionType="8" Encrypted="False" />
  <File Name="4214454775.entxml" CRC32="0xBCFEA078" Size="3811" CompressionType="8" Encrypted="False" />
  <File Name="4215118665.entxml" CRC32="0x26767E50" Size="3809" CompressionType="8" Encrypted="False" />
  <File Name="4229386381.entxml" CRC32="0x3E0E37E5" Size="3821" CompressionType="8" Encrypted="False" />
  <File Name="4233767127.entxml" CRC32="0xD25C7E9D" Size="3826" CompressionType="8" Encrypted="False" />
  <File Name="4257274423.entxml" CRC32="0x48C66265" Size="3826" CompressionType="8" Encrypted="False" />
  <File Name="42600080.entxml" CRC32="0x4ED377CD" Size="3824" CompressionType="8" Encrypted="False" />
  <File Name="4281170811.entxml" CRC32="0xC8F398B2" Size="3823" CompressionType="8" Encrypted="False" />
  <File Name="428451605.entxml" CRC32="0x793F0BBA" Size="3889" CompressionType="8" Encrypted="False" />
  <File Name="4291945229.entxml" CRC32="0x5909BB7C" Size="3818" CompressionType="8" Encrypted="False" />
  <File Name="430972257.entxml" CRC32="0x12AA0A23" Size="3822" CompressionType="8" Encrypted="False" />
  <File Name="454469674.entxml" CRC32="0x2217D12F" Size="3819" CompressionType="8" Encrypted="False" />
  <File Name="469023265.entxml" CRC32="0xE544848D" Size="3822" CompressionType="8" Encrypted="False" />
  <File Name="472780686.entxml" CRC32="0x15393748" Size="3822" CompressionType="8" Encrypted="False" />
  <File Name="484551507.entxml" CRC32="0x57BFB435" Size="3823" CompressionType="8" Encrypted="False" />
  <File Name="500980888.entxml" CRC32="0xD79EC144" Size="3813" CompressionType="8" Encrypted="False" />
  <File Name="501246110.entxml" CRC32="0xF260724F" Size="3820" CompressionType="8" Encrypted="False" />
  <File Name="510012978.entxml" CRC32="0x0C7FC6ED" Size="3825" CompressionType="8" Encrypted="False" />
  <File Name="539589644.entxml" CRC32="0x8913BE2A" Size="3818" CompressionType="8" Encrypted="False" />
  <File Name="54250079.entxml" CRC32="0x95267E69" Size="3823" CompressionType="8" Encrypted="False" />
  <File Name="553301454.entxml" CRC32="0xA1044C9B" Size="3890" CompressionType="8" Encrypted="False" />
  <File Name="564338022.entxml" CRC32="0xC02E48E8" Size="3824" CompressionType="8" Encrypted="False" />
  <File Name="570596596.entxml" CRC32="0x12122B33" Size="3824" CompressionType="8" Encrypted="False" />
  <File Name="575306680.entxml" CRC32="0xD30E47C9" Size="3824" CompressionType="8" Encrypted="False" />
  <File Name="58774215.entxml" CRC32="0x2F8857F3" Size="3825" CompressionType="8" Encrypted="False" />
  <File Name="600130548.entxml" CRC32="0x43E9F224" Size="3888" CompressionType="8" Encrypted="False" />
  <File Name="620954219.entxml" CRC32="0xB0293909" Size="3824" CompressionType="8" Encrypted="False" />
  <File Name="62494870.entxml" CRC32="0x715149C1" Size="3820" CompressionType="8" Encrypted="False" />
  <File Name="632203604.entxml" CRC32="0xD82C6C66" Size="3815" CompressionType="8" Encrypted="False" />
  <File Name="635647123.entxml" CRC32="0xBDACFB62" Size="3830" CompressionType="8" Encrypted="False" />
  <File Name="647688331.entxml" CRC32="0xC31BA38D" Size="3822" CompressionType="8" Encrypted="False" />
  <File Name="672154847.entxml" CRC32="0x8F7FD838" Size="3821" CompressionType="8" Encrypted="False" />
  <File Name="68064973.entxml" CRC32="0xB53257DC" Size="3811" CompressionType="8" Encrypted="False" />
  <File Name="68847610.entxml" CRC32="0x4F30E517" Size="3819" CompressionType="8" Encrypted="False" />
  <File Name="698459327.entxml" CRC32="0x61115E7B" Size="3818" CompressionType="8" Encrypted="False" />
  <File Name="701663827.entxml" CRC32="0xF5D885DD" Size="3824" CompressionType="8" Encrypted="False" />
  <File Name="709581458.entxml" CRC32="0xE595C0D7" Size="3821" CompressionType="8" Encrypted="False" />
  <File Name="717165056.entxml" CRC32="0xF5704833" Size="3822" CompressionType="8" Encrypted="False" />
  <File Name="723126047.entxml" CRC32="0xF9405B0E" Size="3827" CompressionType="8" Encrypted="False" />
  <File Name="755409038.entxml" CRC32="0xE1D1E123" Size="3823" CompressionType="8" Encrypted="False" />
  <File Name="760421331.entxml" CRC32="0x6D36D86E" Size="3820" CompressionType="8" Encrypted="False" />
  <File Name="801073671.entxml" CRC32="0x31893DCB" Size="3821" CompressionType="8" Encrypted="False" />
  <File Name="813240293.entxml" CRC32="0x65BD4ED0" Size="3818" CompressionType="8" Encrypted="False" />
  <File Name="82858705.entxml" CRC32="0xA77D0EA8" Size="3818" CompressionType="8" Encrypted="False" />
  <File Name="856684474.entxml" CRC32="0xD64826C0" Size="3820" CompressionType="8" Encrypted="False" />
  <File Name="85843805.entxml" CRC32="0x2408F374" Size="3821" CompressionType="8" Encrypted="False" />
  <File Name="872219749.entxml" CRC32="0xD94310E8" Size="3822" CompressionType="8" Encrypted="False" />
  <File Name="884836245.entxml" CRC32="0xE8453613" Size="3819" CompressionType="8" Encrypted="False" />
  <File Name="886459201.entxml" CRC32="0xF3DEE600" Size="3821" CompressionType="8" Encrypted="False" />
  <File Name="922173149.entxml" CRC32="0x963B5DBD" Size="3819" CompressionType="8" Encrypted="False" />
  <File Name="930062913.entxml" CRC32="0xF1E39FBC" Size="3822" CompressionType="8" Encrypted="False" />
  <File Name="941901914.entxml" CRC32="0x0BC986BB" Size="3820" CompressionType="8" Encrypted="False" />
  <File Name="953129033.entxml" CRC32="0x620F7CFA" Size="3822" CompressionType="8" Encrypted="False" />
  <File Name="963365586.entxml" CRC32="0xF98D52D1" Size="3825" CompressionType="8" Encrypted="False" />
  <File Name="96740471.entxml" CRC32="0x57FA372D" Size="3816" CompressionType="8" Encrypted="False" />
</Directory>