{
  "_RecordName_": "EntityClassDefinition.NavPoint_SubPoint4",
  "_RecordId_": "4cc3bf59-9411-461e-9540-78ab0cc017bb",
  "_RecordValue_": {
    "_Type_": "EntityClassDefinition",
    "Category": "Default",
    "Icon": "Default.bmp",
    "Invisible": false,
    "BBoxSelection": false,
    "entityDensityClass": null,
    "tags": [],
    "StaticEntityClassData": [],
    "Components": [
      {
        "_Type_": "SEntityComponentObjectMetadataParams",
        "name": "@LOC_EMPTY",
        "hasLocalBounds": true,
        "isDynamic": false,
        "metadata": [
          {
            "_Type_": "SNavPointObjectMetadataParams",
            "starmapRecord": "file://./../../../../libs/foundry/records/starmap/cardinalpoint4.json",
            "locationActionArea": "",
            "permanent": true,
            "showInAllZones": false,
            "allowHierarchyDuplicates": true,
            "saveToLocalPlayerObjectDataBank": false,
            "moveable": false
          }
        ]
      }
    ]
  }
}