{
  "_RecordName_": "MissionBrokerEntry.Tutorial02_Shopping_Area18",
  "_RecordId_": "a265229e-9009-4118-a3dd-1148512b2374",
  "_RecordValue_": {
    "_Type_": "MissionBrokerEntry",
    "notForRelease": false,
    "owner": "file://./../../../../../../libs/foundry/records/devowners/devteams/mct.json",
    "missionModule": "Libs/Subsumption/Missions/PU/PU_Missions/Tutorial/Tutorial02_Shopping.xml",
    "playerFacingDebugName": "",
    "title": "@Tutorial02_MissionTitle",
    "titleHUD": "@Tutorial02_MissionTitle",
    "description": "@Tutorial02_MissionDesc",
    "missionGiver": "@tutorial_from",
    "commsChannelName": "@LOC_UNINITIALIZED",
    "type": "file://./../../../../../../libs/foundry/records/missiontype/pu/priority.json",
    "associatedMissions": [],
    "missionDifficulty": -1,
    "localityAvailable": null,
    "locationMissionAvailable": "file://./../../../../../../libs/foundry/records/starmap/pu/system/stanton/stanton3/starmapobject.stanton3.json",
    "availableDateSchedule": [],
    "onlyAvailableIfAllMissionsNotAvailable": [],
    "missionReward": {
      "_Type_": "MissionReward",
      "reward": 15000,
      "max": 0,
      "plusBonuses": false,
      "currencyType": "UEC",
      "reputationBonus": null
    },
    "partialRewardPayout": null,
    "missionResultReputationRewards": [
      {
        "_Type_": "SReputationAmountListParams",
        "reputationAmounts": []
      },
      {
        "_Type_": "SReputationAmountListParams",
        "reputationAmounts": []
      },
      {
        "_Type_": "SReputationAmountListParams",
        "reputationAmounts": []
      },
      {
        "_Type_": "SReputationAmountListParams",
        "reputationAmounts": []
      },
      {
        "_Type_": "SReputationAmountListParams",
        "reputationAmounts": []
      }
    ],
    "journalEntriesToAddOnComplete": [],
    "journalEntriesToRemoveOnComplete": [],
    "initiallyActive": true,
    "notifyOnAvailable": false,
    "preShowObjectives": false,
    "showAsOffer": false,
    "missionBuyInAmount": 0,
    "refundBuyInOnWithdraw": false,
    "hasCompleteButton": false,
    "onlyOwnerCanComplete": false,
    "handlesAbandonRequest": false,
    "missionModulePerPlayer": true,
    "maxInstances": -1,
    "maxPlayersPerInstance": 1,
    "maxInstancesPerPlayer": 1,
    "canBeShared": false,
    "onceOnly": true,
    "tutorial": true,
    "missionDeadline": {
      "_Type_": "MissionDeadline",
      "missionCompletionTime": 0,
      "missionAutoEnd": false,
      "missionResultAfterTimerEnd": "Failed",
      "remainingTimeToShowTimer": 0,
      "missionEndReason": "@LOC_EMPTY"
    },
    "displayAlliedMarkers": false,
    "availableInPrison": false,
    "failIfSentToPrison": true,
    "failIfBecameCriminal": false,
    "failIfLeavePrison": false,
    "completionTags": {
      "_Type_": "TagList",
      "tags": []
    },
    "applyCompletionTagsOnFailed": false,
    "applyCompletionTagsOnAbandoned": false,
    "requestOnly": false,
    "respawnTime": 0,
    "respawnTimeVariation": 0,
    "instanceHasLifeTime": false,
    "showLifeTimeInMobiGlas": false,
    "instanceLifeTime": 0,
    "instanceLifeTimeVariation": 0,
    "canReacceptAfterAbandoning": false,
    "abandonedCooldownTime": 0,
    "abandonedCooldownTimeVariation": 0,
    "canReacceptAfterFailing": false,
    "hasPersonalCooldown": false,
    "personalCooldownTime": 0,
    "personalCooldownTimeVariation": 0,
    "moduleHandlesOwnShutdown": false,
    "linkedMission": null,
    "missionCompletePerk": null,
    "modifiers": [
      {
        "_Type_": "MissionModifier_ShipKioskFilter",
        "modifierName": "",
        "enabled": true,
        "kioskFilterType": {
          "_Type_": "TagsDNF",
          "terms": [
            {
              "_Type_": "TagsDNFTerm",
              "positiveTags": [
                {
                  "_RecordPath_": "file://./../../../../../../libs/foundry/records/tagdatabase/tagdatabase.tagdatabase.json",
                  "_RecordName_": "Tag.35559c9a-4ac1-4d3f-83ac-83c5795efe43",
                  "_RecordId_": "35559c9a-4ac1-4d3f-83ac-83c5795efe43"
                }
              ],
              "negativeTags": []
            }
          ]
        }
      }
    ],
    "lawfulMission": true,
    "missionGiverRecord": null,
    "invitationMission": null,
    "missionTags": [],
    "missionGiverFragmentTags": "",
    "reputationPrerequisites": {
      "_Type_": "ReputationPrerequisites",
      "wantedLevelJurisdictionOverride": null,
      "wantedLevel": {
        "_Type_": "ReputationPrerequisiteRange",
        "minValue": 0,
        "maxValue": 2
      }
    },
    "reputationRequirements": null,
    "minRequiredMissions": [],
    "requiredMissions": [
      "file://./../../../../../../libs/foundry/records/missionbroker/pu_missions/tutorial/tutorial01_basics_area18.json"
    ],
    "requiredCompletedMissionTags": [],
    "requiredJournalEntries": [],
    "requiredAreaTags": {
      "_Type_": "TagList",
      "tags": []
    },
    "excludedAreaTags": {
      "_Type_": "TagList",
      "tags": []
    },
    "properties": [
      {
        "_Type_": "MissionProperty",
        "missionVariableName": "MissionLocation_BP",
        "extendedTextToken": "Location",
        "value": {
          "_Type_": "MissionPropertyValue_Location",
          "minLocationsToFind": 1,
          "maxLocationsToFind": 1,
          "matchConditions": [
            {
              "_Type_": "DataSetMatchCondition_TagSearch",
              "tagSearch": [
                {
                  "_Type_": "TagSearchTerm",
                  "positiveTags": [
                    {
                      "_RecordPath_": "file://./../../../../../../libs/foundry/records/tagdatabase/tagdatabase.tagdatabase.json",
                      "_RecordName_": "Tag.c238c1bf-4238-4fc5-bc42-14b6bbcab7b0",
                      "_RecordId_": "c238c1bf-4238-4fc5-bc42-14b6bbcab7b0"
                    },
                    {
                      "_RecordPath_": "file://./../../../../../../libs/foundry/records/tagdatabase/tagdatabase.tagdatabase.json",
                      "_RecordName_": "Tag.67508ea1-f2a5-4e1a-a045-2c1378c4b89e",
                      "_RecordId_": "67508ea1-f2a5-4e1a-a045-2c1378c4b89e"
                    }
                  ],
                  "negativeTags": []
                }
              ],
              "tagType": "General"
            }
          ],
          "resourceTags": [],
          "resourcePriority": "Contract",
          "logErrorOnSearchFail": true
        }
      },
      {
        "_Type_": "MissionProperty",
        "missionVariableName": "OutOfRangeDistance_BP",
        "extendedTextToken": "",
        "value": {
          "_Type_": "MissionPropertyValue_Float",
          "options": [
            {
              "_Type_": "MissionPropertyValueOption_Float",
              "textId": "@LOC_UNINITIALIZED",
              "weighting": 1,
              "DEBUG_forceChooseThisOption": false,
              "dependentProperties": [],
              "value": 10000000,
              "variation": 0
            }
          ]
        }
      },
      {
        "_Type_": "MissionProperty",
        "missionVariableName": "MaxServerWaitTime_BP",
        "extendedTextToken": "",
        "value": {
          "_Type_": "MissionPropertyValue_Float",
          "options": [
            {
              "_Type_": "MissionPropertyValueOption_Float",
              "textId": "@LOC_UNINITIALIZED",
              "weighting": 1,
              "DEBUG_forceChooseThisOption": false,
              "dependentProperties": [],
              "value": 600,
              "variation": 0
            }
          ]
        }
      },
      {
        "_Type_": "MissionProperty",
        "missionVariableName": "HabElevatorStopIndex1_BP",
        "extendedTextToken": "",
        "value": {
          "_Type_": "MissionPropertyValue_Integer",
          "options": [
            {
              "_Type_": "MissionPropertyValueOption_Integer",
              "textId": "@LOC_UNINITIALIZED",
              "weighting": 1,
              "DEBUG_forceChooseThisOption": false,
              "dependentProperties": [],
              "value": 6,
              "variation": 0
            }
          ]
        }
      },
      {
        "_Type_": "MissionProperty",
        "missionVariableName": "HabElevatorStopIndex2_BP",
        "extendedTextToken": "",
        "value": {
          "_Type_": "MissionPropertyValue_Integer",
          "options": [
            {
              "_Type_": "MissionPropertyValueOption_Integer",
              "textId": "@LOC_UNINITIALIZED",
              "weighting": 1,
              "DEBUG_forceChooseThisOption": false,
              "dependentProperties": [],
              "value": 11,
              "variation": 0
            }
          ]
        }
      },
      {
        "_Type_": "MissionProperty",
        "missionVariableName": "AreaMapWaitTrimer_BP",
        "extendedTextToken": "",
        "value": {
          "_Type_": "MissionPropertyValue_Float",
          "options": [
            {
              "_Type_": "MissionPropertyValueOption_Float",
              "textId": "@LOC_UNINITIALIZED",
              "weighting": 1,
              "DEBUG_forceChooseThisOption": false,
              "dependentProperties": [],
              "value": 10,
              "variation": 0
            }
          ]
        }
      },
      {
        "_Type_": "MissionProperty",
        "missionVariableName": "",
        "extendedTextToken": "HubFloor",
        "value": {
          "_Type_": "MissionPropertyValue_StringHash",
          "options": [
            {
              "_Type_": "MissionPropertyValueOption_StringHash",
              "textId": "@ui_interactor_ground_floor",
              "weighting": 1,
              "DEBUG_forceChooseThisOption": false,
              "dependentProperties": [],
              "value": ""
            }
          ]
        }
      },
      {
        "_Type_": "MissionProperty",
        "missionVariableName": "",
        "extendedTextToken": "StoreName",
        "value": {
          "_Type_": "MissionPropertyValue_StringHash",
          "options": [
            {
              "_Type_": "MissionPropertyValueOption_StringHash",
              "textId": "@Tutorial_Shop_Area18",
              "weighting": 1,
              "DEBUG_forceChooseThisOption": false,
              "dependentProperties": [],
              "value": ""
            }
          ]
        }
      }
    ],
    "objectiveTokens": [],
    "missionFlow": {
      "_Type_": "MissionFlow",
      "triggers": []
    }
  }
}