<?xml version="1.0" encoding="utf-8"?>
<Directory Name="a18">
  <File Name="a18_ac_tower_int_001.socpak" CRC32="0x524F37CB" Size="73740" CompressionType="0" Encrypted="False" />
  <File Name="a18_central_tiles.socpak" CRC32="0x603DC5EE" Size="472628" CompressionType="0" Encrypted="False" />
  <File Name="a18_central.socpak" CRC32="0xEC2CDB58" Size="4555041" CompressionType="0" Encrypted="False" />
  <File Name="a18_city.socpak" CRC32="0x63D97B86" Size="515379" CompressionType="0" Encrypted="False" />
  <File Name="a18_fleetweek_analytics_bevic_center.socpak" CRC32="0xED229BFA" Size="2981" CompressionType="0" Encrypted="False" />
  <File Name="a18_habtower_lobby.socpak" CRC32="0x94EF06AF" Size="104780" CompressionType="0" Encrypted="False" />
  <File Name="a18_habtower.socpak" CRC32="0xAB61F60C" Size="47869" CompressionType="0" Encrypted="False" />
  <File Name="a18_holidaybox_01.socpak" CRC32="0xEDC7D6FE" Size="35114" CompressionType="0" Encrypted="False" />
  <File Name="a18_holidaybox_02.socpak" CRC32="0x7FF8CEF8" Size="4288" CompressionType="0" Encrypted="False" />
  <File Name="a18_holidayboxes.socpak" CRC32="0x63E6BEDA" Size="486604" CompressionType="0" Encrypted="False" />
  <File Name="a18_hospital_hallway.socpak" CRC32="0xA0DAD7D0" Size="208960" CompressionType="0" Encrypted="False" />
  <File Name="a18_hospital_int.socpak" CRC32="0xE12616B0" Size="354993" CompressionType="0" Encrypted="False" />
  <File Name="a18_hospital.socpak" CRC32="0x4226F309" Size="25880" CompressionType="0" Encrypted="False" />
  <File Name="a18_mural.socpak" CRC32="0x0B7086FC" Size="7891" CompressionType="0" Encrypted="False" />
  <File Name="a18_sp_ext.socpak" CRC32="0x7AAAED67" Size="628659" CompressionType="0" Encrypted="False" />
  <File Name="a18_sp_int.socpak" CRC32="0x4370ADA3" Size="984590" CompressionType="0" Encrypted="False" />
  <File Name="a18_tiles_downtown_1x1_a.socpak" CRC32="0x8DD676FC" Size="79227" CompressionType="0" Encrypted="False" />
  <File Name="a18_tiles_downtown_1x1_b.socpak" CRC32="0x791A9933" Size="71444" CompressionType="0" Encrypted="False" />
  <File Name="a18_tiles_downtown_2x2_a.socpak" CRC32="0x8AD830A1" Size="130006" CompressionType="0" Encrypted="False" />
  <File Name="a18_tiles_downtown_3x3_a.socpak" CRC32="0x3600596D" Size="220837" CompressionType="0" Encrypted="False" />
  <File Name="a18_tiles_downtown_3x3_b.socpak" CRC32="0x09922FD9" Size="224126" CompressionType="0" Encrypted="False" />
  <File Name="a18_tiles_ring_1x1_a.socpak" CRC32="0x51FEEFB7" Size="66871" CompressionType="0" Encrypted="False" />
  <File Name="a18_tiles_ring_1x1_fleetweek_2023.socpak" CRC32="0x25EA4E55" Size="848775" CompressionType="0" Encrypted="False" />
  <File Name="a18_tiles_ring_1x1_fleetweek.socpak" CRC32="0x448E0D9E" Size="1078658" CompressionType="0" Encrypted="False" />
  <File Name="a18.socpak" CRC32="0xECAC8704" Size="1900233" CompressionType="0" Encrypted="False" />
  <File Name="scripcollectables.socpak" CRC32="0x294FC3ED" Size="74104" CompressionType="0" Encrypted="False" />
  <File Name="stanton3_planet_only.socpak" CRC32="0xE276CF21" Size="2103767" CompressionType="0" Encrypted="False" />
</Directory>