<?xml version="1.0" encoding="utf-8"?>
<Directory Name="entdata">
  <File Name="1001804873.entxml" CRC32="0xD48C8944" Size="3821" CompressionType="8" Encrypted="False" />
  <File Name="1030278340.entxml" CRC32="0xCDD68D52" Size="3791" CompressionType="8" Encrypted="False" />
  <File Name="1037288857.entxml" CRC32="0x731C498F" Size="3821" CompressionType="8" Encrypted="False" />
  <File Name="108233180.entxml" CRC32="0x9B387565" Size="3819" CompressionType="8" Encrypted="False" />
  <File Name="1121520924.entxml" CRC32="0x52EDE56C" Size="3746" CompressionType="8" Encrypted="False" />
  <File Name="1162813585.entxml" CRC32="0x9C008906" Size="3752" CompressionType="8" Encrypted="False" />
  <File Name="1169402007.entxml" CRC32="0xDB151BCF" Size="3862" CompressionType="8" Encrypted="False" />
  <File Name="1220843728.entxml" CRC32="0xE95C105B" Size="3787" CompressionType="8" Encrypted="False" />
  <File Name="1242654413.entxml" CRC32="0x55E43DAF" Size="3792" CompressionType="8" Encrypted="False" />
  <File Name="1287953020.entxml" CRC32="0xD5C25B07" Size="3745" CompressionType="8" Encrypted="False" />
  <File Name="1295079389.entxml" CRC32="0xBE97E0E3" Size="3751" CompressionType="8" Encrypted="False" />
  <File Name="1308155214.entxml" CRC32="0x6C286311" Size="3823" CompressionType="8" Encrypted="False" />
  <File Name="1317486421.entxml" CRC32="0xC5CC499D" Size="3762" CompressionType="8" Encrypted="False" />
  <File Name="1330482692.entxml" CRC32="0x9AC9D3F3" Size="3746" CompressionType="8" Encrypted="False" />
  <File Name="1351808865.entxml" CRC32="0x338D9F86" Size="3749" CompressionType="8" Encrypted="False" />
  <File Name="136351281.entxml" CRC32="0x9ADF5A77" Size="3784" CompressionType="8" Encrypted="False" />
  <File Name="1392635658.entxml" CRC32="0x2BEB3157" Size="3820" CompressionType="8" Encrypted="False" />
  <File Name="1408308296.entxml" CRC32="0xA8EEC0EA" Size="3820" CompressionType="8" Encrypted="False" />
  <File Name="1409026264.entxml" CRC32="0x43609D45" Size="3793" CompressionType="8" Encrypted="False" />
  <File Name="1436387904.entxml" CRC32="0x9FCBA31A" Size="3821" CompressionType="8" Encrypted="False" />
  <File Name="1528306049.entxml" CRC32="0x1AC45EF3" Size="3744" CompressionType="8" Encrypted="False" />
  <File Name="152837652.entxml" CRC32="0x72B7DC8A" Size="3816" CompressionType="8" Encrypted="False" />
  <File Name="1604853648.entxml" CRC32="0x0A860905" Size="3815" CompressionType="8" Encrypted="False" />
  <File Name="1641681937.entxml" CRC32="0xA520239B" Size="3868" CompressionType="8" Encrypted="False" />
  <File Name="168675033.entxml" CRC32="0x7E6704DF" Size="3864" CompressionType="8" Encrypted="False" />
  <File Name="1710261931.entxml" CRC32="0x2D11BCD2" Size="3865" CompressionType="8" Encrypted="False" />
  <File Name="1718606439.entxml" CRC32="0xEDB6E921" Size="3745" CompressionType="8" Encrypted="False" />
  <File Name="171881491.entxml" CRC32="0x7F87A48D" Size="3752" CompressionType="8" Encrypted="False" />
  <File Name="1727914754.entxml" CRC32="0x3196F7BA" Size="3821" CompressionType="8" Encrypted="False" />
  <File Name="1728549090.entxml" CRC32="0x5CBE3945" Size="3816" CompressionType="8" Encrypted="False" />
  <File Name="1788199196.entxml" CRC32="0x38205B8E" Size="3816" CompressionType="8" Encrypted="False" />
  <File Name="1822897654.entxml" CRC32="0x583AECF4" Size="3866" CompressionType="8" Encrypted="False" />
  <File Name="1827344749.entxml" CRC32="0x623260A2" Size="3817" CompressionType="8" Encrypted="False" />
  <File Name="1828294387.entxml" CRC32="0x8FB4679B" Size="3861" CompressionType="8" Encrypted="False" />
  <File Name="1835409417.entxml" CRC32="0x6CAF0EB9" Size="3820" CompressionType="8" Encrypted="False" />
  <File Name="1842073298.entxml" CRC32="0x2AE52ABB" Size="3760" CompressionType="8" Encrypted="False" />
  <File Name="1875817752.entxml" CRC32="0xC0AB6939" Size="3750" CompressionType="8" Encrypted="False" />
  <File Name="1913191168.entxml" CRC32="0x00F7C991" Size="3864" CompressionType="8" Encrypted="False" />
  <File Name="1946834058.entxml" CRC32="0xB77B33AD" Size="3863" CompressionType="8" Encrypted="False" />
  <File Name="2110239847.entxml" CRC32="0xE204F787" Size="3747" CompressionType="8" Encrypted="False" />
  <File Name="2126937792.entxml" CRC32="0x4F109173" Size="3820" CompressionType="8" Encrypted="False" />
  <File Name="2176869983.entxml" CRC32="0x5EAC66BB" Size="3824" CompressionType="8" Encrypted="False" />
  <File Name="2192392899.entxml" CRC32="0x40EB707A" Size="3821" CompressionType="8" Encrypted="False" />
  <File Name="2239365455.entxml" CRC32="0xAA069031" Size="3820" CompressionType="8" Encrypted="False" />
  <File Name="2277331214.entxml" CRC32="0x83703DD8" Size="3817" CompressionType="8" Encrypted="False" />
  <File Name="2277378782.entxml" CRC32="0x2D27168A" Size="3749" CompressionType="8" Encrypted="False" />
  <File Name="2314956486.entxml" CRC32="0x2CD63E15" Size="3818" CompressionType="8" Encrypted="False" />
  <File Name="2395193589.entxml" CRC32="0x77E86FF9" Size="3821" CompressionType="8" Encrypted="False" />
  <File Name="2416784676.entxml" CRC32="0x20158A38" Size="3824" CompressionType="8" Encrypted="False" />
  <File Name="2432166169.entxml" CRC32="0xFEFA86F0" Size="3819" CompressionType="8" Encrypted="False" />
  <File Name="2457788113.entxml" CRC32="0x73B4D97E" Size="3818" CompressionType="8" Encrypted="False" />
  <File Name="2469417815.entxml" CRC32="0x4E8AE04E" Size="3864" CompressionType="8" Encrypted="False" />
  <File Name="2484331631.entxml" CRC32="0x8D307657" Size="3748" CompressionType="8" Encrypted="False" />
  <File Name="2491154103.entxml" CRC32="0x875DBA4E" Size="3784" CompressionType="8" Encrypted="False" />
  <File Name="2491285237.entxml" CRC32="0x55EC0BD7" Size="3783" CompressionType="8" Encrypted="False" />
  <File Name="2533322756.entxml" CRC32="0x41167BE3" Size="3745" CompressionType="8" Encrypted="False" />
  <File Name="264972859.entxml" CRC32="0x1C167616" Size="3791" CompressionType="8" Encrypted="False" />
  <File Name="2650863433.entxml" CRC32="0xAEBCD09C" Size="3750" CompressionType="8" Encrypted="False" />
  <File Name="2718870840.entxml" CRC32="0x0B702C0A" Size="3862" CompressionType="8" Encrypted="False" />
  <File Name="2789785673.entxml" CRC32="0x172AE2D5" Size="3779" CompressionType="8" Encrypted="False" />
  <File Name="2808894343.entxml" CRC32="0x7CF09408" Size="3759" CompressionType="8" Encrypted="False" />
  <File Name="2812933917.entxml" CRC32="0x4800851D" Size="3749" CompressionType="8" Encrypted="False" />
  <File Name="2899185077.entxml" CRC32="0x453C8B36" Size="3744" CompressionType="8" Encrypted="False" />
  <File Name="2991576565.entxml" CRC32="0x762A93A1" Size="3817" CompressionType="8" Encrypted="False" />
  <File Name="3028947251.entxml" CRC32="0xC6D5BA97" Size="3826" CompressionType="8" Encrypted="False" />
  <File Name="3233545036.entxml" CRC32="0x4B971D33" Size="3820" CompressionType="8" Encrypted="False" />
  <File Name="3254721317.entxml" CRC32="0x5C74C384" Size="3819" CompressionType="8" Encrypted="False" />
  <File Name="3269001883.entxml" CRC32="0x578EBF21" Size="3819" CompressionType="8" Encrypted="False" />
  <File Name="3272798096.entxml" CRC32="0x5A02B0F2" Size="3748" CompressionType="8" Encrypted="False" />
  <File Name="3297011045.entxml" CRC32="0x531B085B" Size="3743" CompressionType="8" Encrypted="False" />
  <File Name="3418772293.entxml" CRC32="0x21EA2A20" Size="3751" CompressionType="8" Encrypted="False" />
  <File Name="343434901.entxml" CRC32="0x1914AE5B" Size="3761" CompressionType="8" Encrypted="False" />
  <File Name="34366.entxml" CRC32="0x4F71E409" Size="3865" CompressionType="8" Encrypted="False" />
  <File Name="3441011805.entxml" CRC32="0x98DEA3AD" Size="3749" CompressionType="8" Encrypted="False" />
  <File Name="3460006284.entxml" CRC32="0x2EA59D60" Size="3751" CompressionType="8" Encrypted="False" />
  <File Name="3469113364.entxml" CRC32="0xCD5EB5ED" Size="3822" CompressionType="8" Encrypted="False" />
  <File Name="3476774717.entxml" CRC32="0x0E9C492A" Size="3825" CompressionType="8" Encrypted="False" />
  <File Name="3498205268.entxml" CRC32="0x02FD0309" Size="3793" CompressionType="8" Encrypted="False" />
  <File Name="355199042.entxml" CRC32="0x6031801A" Size="3776" CompressionType="8" Encrypted="False" />
  <File Name="3557108049.entxml" CRC32="0x6D9DDD36" Size="3863" CompressionType="8" Encrypted="False" />
  <File Name="358571993.entxml" CRC32="0x49E636F1" Size="3740" CompressionType="8" Encrypted="False" />
  <File Name="3605695527.entxml" CRC32="0x01DC1E9B" Size="3777" CompressionType="8" Encrypted="False" />
  <File Name="3616391368.entxml" CRC32="0x27C3A70E" Size="3751" CompressionType="8" Encrypted="False" />
  <File Name="3626534731.entxml" CRC32="0xE2F327E6" Size="3864" CompressionType="8" Encrypted="False" />
  <File Name="363983480.entxml" CRC32="0x76ED8A68" Size="3746" CompressionType="8" Encrypted="False" />
  <File Name="3682727873.entxml" CRC32="0x9C2120C9" Size="3742" CompressionType="8" Encrypted="False" />
  <File Name="3750656096.entxml" CRC32="0x1C6E59FF" Size="3821" CompressionType="8" Encrypted="False" />
  <File Name="3756482869.entxml" CRC32="0xE31204FF" Size="3817" CompressionType="8" Encrypted="False" />
  <File Name="376074619.entxml" CRC32="0xF9AC40B0" Size="3821" CompressionType="8" Encrypted="False" />
  <File Name="3798064155.entxml" CRC32="0x87173076" Size="3865" CompressionType="8" Encrypted="False" />
  <File Name="3805454435.entxml" CRC32="0x0D81AC23" Size="3822" CompressionType="8" Encrypted="False" />
  <File Name="3819124393.entxml" CRC32="0x27027832" Size="3761" CompressionType="8" Encrypted="False" />
  <File Name="3856161099.entxml" CRC32="0xDA262B82" Size="3821" CompressionType="8" Encrypted="False" />
  <File Name="3880110012.entxml" CRC32="0xFBF8E0A1" Size="3821" CompressionType="8" Encrypted="False" />
  <File Name="3892833341.entxml" CRC32="0xE744B7EA" Size="3819" CompressionType="8" Encrypted="False" />
  <File Name="3933925815.entxml" CRC32="0x478A999B" Size="3862" CompressionType="8" Encrypted="False" />
  <File Name="3973338651.entxml" CRC32="0xC62934E9" Size="3826" CompressionType="8" Encrypted="False" />
  <File Name="398380853.entxml" CRC32="0x4243EA4D" Size="3820" CompressionType="8" Encrypted="False" />
  <File Name="4008104079.entxml" CRC32="0xE2649428" Size="3821" CompressionType="8" Encrypted="False" />
  <File Name="4039512872.entxml" CRC32="0x533DF524" Size="3819" CompressionType="8" Encrypted="False" />
  <File Name="4086069944.entxml" CRC32="0xD16DCDBE" Size="3746" CompressionType="8" Encrypted="False" />
  <File Name="4109136223.entxml" CRC32="0x1176834C" Size="3820" CompressionType="8" Encrypted="False" />
  <File Name="411472368.entxml" CRC32="0x86F44F29" Size="3820" CompressionType="8" Encrypted="False" />
  <File Name="4146346664.entxml" CRC32="0x0E852DAD" Size="3863" CompressionType="8" Encrypted="False" />
  <File Name="4160676561.entxml" CRC32="0x9A957102" Size="3821" CompressionType="8" Encrypted="False" />
  <File Name="4176555857.entxml" CRC32="0x47EE6DB7" Size="3821" CompressionType="8" Encrypted="False" />
  <File Name="4178726332.entxml" CRC32="0xE02AED9D" Size="3861" CompressionType="8" Encrypted="False" />
  <File Name="4196087745.entxml" CRC32="0xEC910FD3" Size="3819" CompressionType="8" Encrypted="False" />
  <File Name="4201216796.entxml" CRC32="0x487B1267" Size="3749" CompressionType="8" Encrypted="False" />
  <File Name="4268326831.entxml" CRC32="0xEB7DECD1" Size="3819" CompressionType="8" Encrypted="False" />
  <File Name="4276554270.entxml" CRC32="0x834663C4" Size="3820" CompressionType="8" Encrypted="False" />
  <File Name="443805000.entxml" CRC32="0x02BABDEC" Size="3864" CompressionType="8" Encrypted="False" />
  <File Name="512301092.entxml" CRC32="0x0DE86CF9" Size="3816" CompressionType="8" Encrypted="False" />
  <File Name="513229511.entxml" CRC32="0xD619D25F" Size="3818" CompressionType="8" Encrypted="False" />
  <File Name="557766702.entxml" CRC32="0xC996F3E0" Size="3823" CompressionType="8" Encrypted="False" />
  <File Name="607325164.entxml" CRC32="0xDE89E621" Size="3819" CompressionType="8" Encrypted="False" />
  <File Name="614711942.entxml" CRC32="0x380FB303" Size="3820" CompressionType="8" Encrypted="False" />
  <File Name="617540271.entxml" CRC32="0xF89C69E5" Size="3748" CompressionType="8" Encrypted="False" />
  <File Name="671682347.entxml" CRC32="0xCEC96AD5" Size="3817" CompressionType="8" Encrypted="False" />
  <File Name="673131479.entxml" CRC32="0xD71E1847" Size="3823" CompressionType="8" Encrypted="False" />
  <File Name="680085935.entxml" CRC32="0x3E24419C" Size="3822" CompressionType="8" Encrypted="False" />
  <File Name="688623307.entxml" CRC32="0x542D9E62" Size="3815" CompressionType="8" Encrypted="False" />
  <File Name="695823893.entxml" CRC32="0xF3626E81" Size="3816" CompressionType="8" Encrypted="False" />
  <File Name="778697422.entxml" CRC32="0xFE5A8B74" Size="3820" CompressionType="8" Encrypted="False" />
  <File Name="80728700.entxml" CRC32="0xFA21E66F" Size="3752" CompressionType="8" Encrypted="False" />
  <File Name="841258708.entxml" CRC32="0xDD608CA7" Size="3794" CompressionType="8" Encrypted="False" />
  <File Name="84448645.entxml" CRC32="0xAA790AE5" Size="3822" CompressionType="8" Encrypted="False" />
  <File Name="845828772.entxml" CRC32="0xE542D9AA" Size="3751" CompressionType="8" Encrypted="False" />
  <File Name="862233420.entxml" CRC32="0xC9E8558A" Size="3777" CompressionType="8" Encrypted="False" />
  <File Name="887025101.entxml" CRC32="0x021B651F" Size="3751" CompressionType="8" Encrypted="False" />
  <File Name="906009558.entxml" CRC32="0xE068EB31" Size="3818" CompressionType="8" Encrypted="False" />
  <File Name="959133726.entxml" CRC32="0x36E3167E" Size="3747" CompressionType="8" Encrypted="False" />
</Directory>