<?xml version="1.0" encoding="utf-8"?>
<Directory Name="entdata">
  <File Name="1068584879.entxml" CRC32="0x9783B8B5" Size="3655" CompressionType="8" Encrypted="False" />
  <File Name="1131314717.entxml" CRC32="0xDFA7EDF3" Size="3652" CompressionType="8" Encrypted="False" />
  <File Name="1171658951.entxml" CRC32="0x4E81620A" Size="3715" CompressionType="8" Encrypted="False" />
  <File Name="1184397342.entxml" CRC32="0xB4ABD0B5" Size="3704" CompressionType="8" Encrypted="False" />
  <File Name="1185657214.entxml" CRC32="0xC17866C4" Size="3670" CompressionType="8" Encrypted="False" />
  <File Name="1235580969.entxml" CRC32="0x0B2CBAF8" Size="3698" CompressionType="8" Encrypted="False" />
  <File Name="133060009.entxml" CRC32="0x8635FE8D" Size="3664" CompressionType="8" Encrypted="False" />
  <File Name="1381184022.entxml" CRC32="0x01395258" Size="3865" CompressionType="8" Encrypted="False" />
  <File Name="1534820293.entxml" CRC32="0xA57BF957" Size="3607" CompressionType="8" Encrypted="False" />
  <File Name="1732380875.entxml" CRC32="0xDD746514" Size="3639" CompressionType="8" Encrypted="False" />
  <File Name="1864955789.entxml" CRC32="0x46A3DBC2" Size="3665" CompressionType="8" Encrypted="False" />
  <File Name="1927493909.entxml" CRC32="0x0A15F05D" Size="3678" CompressionType="8" Encrypted="False" />
  <File Name="2071326503.entxml" CRC32="0x8D9CAE28" Size="3658" CompressionType="8" Encrypted="False" />
  <File Name="2245794279.entxml" CRC32="0x1190049F" Size="3589" CompressionType="8" Encrypted="False" />
  <File Name="225510439.entxml" CRC32="0x299814B0" Size="3695" CompressionType="8" Encrypted="False" />
  <File Name="2324622732.entxml" CRC32="0xD91B2CEB" Size="3703" CompressionType="8" Encrypted="False" />
  <File Name="2530804123.entxml" CRC32="0xA820517C" Size="3672" CompressionType="8" Encrypted="False" />
  <File Name="2558046098.entxml" CRC32="0xB0124AA0" Size="3557" CompressionType="8" Encrypted="False" />
  <File Name="2571272688.entxml" CRC32="0xEAE05F7D" Size="3695" CompressionType="8" Encrypted="False" />
  <File Name="2646776823.entxml" CRC32="0x0CB17E60" Size="3646" CompressionType="8" Encrypted="False" />
  <File Name="269219296.entxml" CRC32="0xC6BE855C" Size="3614" CompressionType="8" Encrypted="False" />
  <File Name="274058199.entxml" CRC32="0x9564ADBA" Size="3710" CompressionType="8" Encrypted="False" />
  <File Name="2921863371.entxml" CRC32="0x4841D7EF" Size="3636" CompressionType="8" Encrypted="False" />
  <File Name="3303288283.entxml" CRC32="0x170959D8" Size="3638" CompressionType="8" Encrypted="False" />
  <File Name="3313793398.entxml" CRC32="0xBD0F421A" Size="3503" CompressionType="8" Encrypted="False" />
  <File Name="3417769965.entxml" CRC32="0x0CA52998" Size="3637" CompressionType="8" Encrypted="False" />
  <File Name="3533881084.entxml" CRC32="0xF5462ABE" Size="3649" CompressionType="8" Encrypted="False" />
  <File Name="3723514494.entxml" CRC32="0xA78087F4" Size="3718" CompressionType="8" Encrypted="False" />
  <File Name="3776013565.entxml" CRC32="0x0432E0A9" Size="3668" CompressionType="8" Encrypted="False" />
  <File Name="3907851358.entxml" CRC32="0xF8892DCF" Size="3667" CompressionType="8" Encrypted="False" />
  <File Name="3936235911.entxml" CRC32="0x08BB37AD" Size="3863" CompressionType="8" Encrypted="False" />
  <File Name="398734833.entxml" CRC32="0x6D28A580" Size="3866" CompressionType="8" Encrypted="False" />
  <File Name="3999560077.entxml" CRC32="0x5C86BAF8" Size="3713" CompressionType="8" Encrypted="False" />
  <File Name="4015162685.entxml" CRC32="0x80B1B704" Size="3633" CompressionType="8" Encrypted="False" />
  <File Name="4102356620.entxml" CRC32="0x427830B5" Size="3697" CompressionType="8" Encrypted="False" />
  <File Name="4148693771.entxml" CRC32="0xF2A03988" Size="3651" CompressionType="8" Encrypted="False" />
  <File Name="4187778628.entxml" CRC32="0x5C856877" Size="3693" CompressionType="8" Encrypted="False" />
  <File Name="4249446680.entxml" CRC32="0x3AF21956" Size="3676" CompressionType="8" Encrypted="False" />
  <File Name="70254919.entxml" CRC32="0xA1D7D011" Size="3671" CompressionType="8" Encrypted="False" />
  <File Name="703042995.entxml" CRC32="0x1DAE5A8A" Size="3681" CompressionType="8" Encrypted="False" />
  <File Name="882501010.entxml" CRC32="0x16542E5F" Size="3603" CompressionType="8" Encrypted="False" />
  <File Name="969012656.entxml" CRC32="0xF010BB24" Size="3638" CompressionType="8" Encrypted="False" />
</Directory>