{
  "_RecordName_": "TintPaletteTree.racing_blue_white_blue",
  "_RecordId_": "3f9d892e-b059-45ae-b2bf-65e0321683bf",
  "_RecordValue_": {
    "_Type_": "TintPaletteTree",
    "root": {
      "_Type_": "TintPalette",
      "name": "racing_blue_white_blue",
      "children": [],
      "inheritsParams": false,
      "entryA": {
        "_Type_": "TintEntry",
        "tintColor": {
          "_Type_": "SRGB8",
          "r": 0,
          "g": 0,
          "b": 0
        },
        "specColor": {
          "_Type_": "SRGB8",
          "r": 94,
          "g": 161,
          "b": 234
        },
        "glossiness": 168
      },
      "entryB": {
        "_Type_": "TintEntry",
        "tintColor": {
          "_Type_": "SRGB8",
          "r": 210,
          "g": 210,
          "b": 210
        },
        "specColor": {
          "_Type_": "SRGB8",
          "r": 59,
          "g": 59,
          "b": 59
        },
        "glossiness": 188
      },
      "entryC": {
        "_Type_": "TintEntry",
        "tintColor": {
          "_Type_": "SRGB8",
          "r": 0,
          "g": 0,
          "b": 0
        },
        "specColor": {
          "_Type_": "SRGB8",
          "r": 94,
          "g": 161,
          "b": 234
        },
        "glossiness": 173
      },
      "glassColor": {
        "_Type_": "SRGB8",
        "r": 60,
        "g": 60,
        "b": 60
      },
      "decalTexture": "",
      "decalColorR": {
        "_Type_": "SRGB8",
        "r": 185,
        "g": 185,
        "b": 185
      },
      "decalColorG": {
        "_Type_": "SRGB8",
        "r": 255,
        "g": 255,
        "b": 255
      },
      "decalColorB": {
        "_Type_": "SRGB8",
        "r": 255,
        "g": 255,
        "b": 255
      }
    },
    "templateTree": null
  }
}